[
  {
    "AtomicNumber": "1",
    "ElementName": "Hydrogen",
    "Symbol": "H",
    "AtomicWeight": "1.00794",
    "Period": "1",
    "Group": "1",
    "IonicRadius": "0.012",
    "AtomicRadius": "0.79",
    "Electronegativity": "2.2",
    "FirstIonizationPotential": "13.5984",
    "Density": "0.00008988",
    "MeltingPoint": "14.175",
    "BoilingPoint": "20.28",
    "Isotopes": "3",
    "SpecificHeatCapacity": "14.304",
    "ElectronConfiguration": "1s1",
    "DisplayRow": "1",
    "DisplayColumn": "1",
    "Id": 1,
    "Guid": "8b9e6898-bf66-459b-8ded-e557cf0799b4",
    "TimeAdded": "2023-09-21T04:51:35.566783+00:00",
    "UserAddedId": 1,
    "TimeModified": "2023-09-21T04:51:35.566783+00:00",
    "UserModifiedId": 1,
    "IsActive": true
  },
  {
    "AtomicNumber": "2",
    "ElementName": "Helium",
    "Symbol": "He",
    "AtomicWeight": "4.002602",
    "Period": "1",
    "Group": "18",
    "IonicRadius": "",
    "AtomicRadius": "0.49",
    "Electronegativity": "",
    "FirstIonizationPotential": "24.5874",
    "Density": "0.0001785",
    "MeltingPoint": "",
    "BoilingPoint": "4.22",
    "Isotopes": "5",
    "SpecificHeatCapacity": "5.193",
    "ElectronConfiguration": "1s2",
    "DisplayRow": "1",
    "DisplayColumn": "18",
    "Id": 2,
    "Guid": "41e0a85d-d50f-462a-9de9-a287713589d9",
    "TimeAdded": "2023-09-21T04:51:35.566783+00:00",
    "UserAddedId": 1,
    "TimeModified": "2023-09-21T04:51:35.566783+00:00",
    "UserModifiedId": 1,
    "IsActive": true
  },
  {
    "AtomicNumber": "3",
    "ElementName": "Lithium",
    "Symbol": "Li",
    "AtomicWeight": "6.941",
    "Period": "2",
    "Group": "1",
    "IonicRadius": "0.76",
    "AtomicRadius": "2.1",
    "Electronegativity": "0.98",
    "FirstIonizationPotential": "5.3917",
    "Density": "0.534",
    "MeltingPoint": "453.85",
    "BoilingPoint": "1615",
    "Isotopes": "5",
    "SpecificHeatCapacity": "3.582",
    "ElectronConfiguration": "[He] 2s1",
    "DisplayRow": "2",
    "DisplayColumn": "1",
    "Id": 3,
    "Guid": "5535557f-44bd-42d4-96b9-950fa81864a6",
    "TimeAdded": "2023-09-21T04:51:35.566783+00:00",
    "UserAddedId": 1,
    "TimeModified": "2023-09-21T04:51:35.566783+00:00",
    "UserModifiedId": 1,
    "IsActive": true
  },
  {
    "AtomicNumber": "4",
    "ElementName": "Beryllium",
    "Symbol": "Be",
    "AtomicWeight": "9.012182",
    "Period": "2",
    "Group": "2",
    "IonicRadius": "0.35",
    "AtomicRadius": "1.4",
    "Electronegativity": "1.57",
    "FirstIonizationPotential": "9.3227",
    "Density": "1.85",
    "MeltingPoint": "1560.15",
    "BoilingPoint": "2742",
    "Isotopes": "6",
    "SpecificHeatCapacity": "1.825",
    "ElectronConfiguration": "[He] 2s2",
    "DisplayRow": "2",
    "DisplayColumn": "2",
    "Id": 4,
    "Guid": "43becbd9-857d-4e46-b3ea-4e8c9fe13e7e",
    "TimeAdded": "2023-09-21T04:51:35.566783+00:00",
    "UserAddedId": 1,
    "TimeModified": "2023-09-21T04:51:35.566783+00:00",
    "UserModifiedId": 1,
    "IsActive": true
  },
  {
    "AtomicNumber": "5",
    "ElementName": "Boron",
    "Symbol": "B",
    "AtomicWeight": "10.811",
    "Period": "2",
    "Group": "13",
    "IonicRadius": "0.23",
    "AtomicRadius": "1.2",
    "Electronegativity": "2.04",
    "FirstIonizationPotential": "8.298",
    "Density": "2.34",
    "MeltingPoint": "2573.15",
    "BoilingPoint": "4200",
    "Isotopes": "6",
    "SpecificHeatCapacity": "1.026",
    "ElectronConfiguration": "[He] 2s2 2p1",
    "DisplayRow": "2",
    "DisplayColumn": "13",
    "Id": 5,
    "Guid": "cfe0d3e1-f509-4b5e-ad81-d11ed8772517",
    "TimeAdded": "2023-09-21T04:51:35.566783+00:00",
    "UserAddedId": 1,
    "TimeModified": "2023-09-21T04:51:35.566783+00:00",
    "UserModifiedId": 1,
    "IsActive": true
  },
  {
    "AtomicNumber": "6",
    "ElementName": "Carbon",
    "Symbol": "C",
    "AtomicWeight": "12.0107",
    "Period": "2",
    "Group": "14",
    "IonicRadius": "",
    "AtomicRadius": "0.91",
    "Electronegativity": "2.55",
    "FirstIonizationPotential": "11.2603",
    "Density": "2.267",
    "MeltingPoint": "3948.15",
    "BoilingPoint": "4300",
    "Isotopes": "7",
    "SpecificHeatCapacity": "0.709",
    "ElectronConfiguration": "[He] 2s2 2p2",
    "DisplayRow": "2",
    "DisplayColumn": "14",
    "Id": 6,
    "Guid": "e44e9d56-918c-4094-a5e6-ea00bd099fc1",
    "TimeAdded": "2023-09-21T04:51:35.566783+00:00",
    "UserAddedId": 1,
    "TimeModified": "2023-09-21T04:51:35.566783+00:00",
    "UserModifiedId": 1,
    "IsActive": true
  },
  {
    "AtomicNumber": "7",
    "ElementName": "Nitrogen",
    "Symbol": "N",
    "AtomicWeight": "14.0067",
    "Period": "2",
    "Group": "15",
    "IonicRadius": "0.13",
    "AtomicRadius": "0.75",
    "Electronegativity": "3.04",
    "FirstIonizationPotential": "14.5341",
    "Density": "0.0012506",
    "MeltingPoint": "63.29",
    "BoilingPoint": "77.36",
    "Isotopes": "8",
    "SpecificHeatCapacity": "1.04",
    "ElectronConfiguration": "[He] 2s2 2p3",
    "DisplayRow": "2",
    "DisplayColumn": "15",
    "Id": 7,
    "Guid": "e78c981e-0adc-43ca-9a66-938cad7a8690",
    "TimeAdded": "2023-09-21T04:51:35.566783+00:00",
    "UserAddedId": 1,
    "TimeModified": "2023-09-21T04:51:35.566783+00:00",
    "UserModifiedId": 1,
    "IsActive": true
  },
  {
    "AtomicNumber": "8",
    "ElementName": "Oxygen",
    "Symbol": "O",
    "AtomicWeight": "15.9994",
    "Period": "2",
    "Group": "16",
    "IonicRadius": "1.4",
    "AtomicRadius": "0.65",
    "Electronegativity": "3.44",
    "FirstIonizationPotential": "13.6181",
    "Density": "0.001429",
    "MeltingPoint": "50.5",
    "BoilingPoint": "90.2",
    "Isotopes": "8",
    "SpecificHeatCapacity": "0.918",
    "ElectronConfiguration": "[He] 2s2 2p4",
    "DisplayRow": "2",
    "DisplayColumn": "16",
    "Id": 8,
    "Guid": "5b59cfcb-0d7d-486b-b13a-d007ecb4778c",
    "TimeAdded": "2023-09-21T04:51:35.566783+00:00",
    "UserAddedId": 1,
    "TimeModified": "2023-09-21T04:51:35.566783+00:00",
    "UserModifiedId": 1,
    "IsActive": true
  },
  {
    "AtomicNumber": "9",
    "ElementName": "Fluorine",
    "Symbol": "F",
    "AtomicWeight": "18.9984032",
    "Period": "2",
    "Group": "17",
    "IonicRadius": "1.3",
    "AtomicRadius": "0.57",
    "Electronegativity": "3.98",
    "FirstIonizationPotential": "17.4228",
    "Density": "0.001696",
    "MeltingPoint": "53.63",
    "BoilingPoint": "85.03",
    "Isotopes": "6",
    "SpecificHeatCapacity": "0.824",
    "ElectronConfiguration": "[He] 2s2 2p5",
    "DisplayRow": "2",
    "DisplayColumn": "17",
    "Id": 9,
    "Guid": "24150b80-68c9-4f6f-b6d1-7ff9e764ac4d",
    "TimeAdded": "2023-09-21T04:51:35.566783+00:00",
    "UserAddedId": 1,
    "TimeModified": "2023-09-21T04:51:35.566783+00:00",
    "UserModifiedId": 1,
    "IsActive": true
  },
  {
    "AtomicNumber": "10",
    "ElementName": "Neon",
    "Symbol": "Ne",
    "AtomicWeight": "20.1797",
    "Period": "2",
    "Group": "18",
    "IonicRadius": "",
    "AtomicRadius": "0.51",
    "Electronegativity": "",
    "FirstIonizationPotential": "21.5645",
    "Density": "0.0008999",
    "MeltingPoint": "24.703",
    "BoilingPoint": "27.07",
    "Isotopes": "8",
    "SpecificHeatCapacity": "1.03",
    "ElectronConfiguration": "[He] 2s2 2p6",
    "DisplayRow": "2",
    "DisplayColumn": "18",
    "Id": 10,
    "Guid": "7a74c249-ceba-4158-a718-b462ee343b38",
    "TimeAdded": "2023-09-21T04:51:35.566783+00:00",
    "UserAddedId": 1,
    "TimeModified": "2023-09-21T04:51:35.566783+00:00",
    "UserModifiedId": 1,
    "IsActive": true
  },
  {
    "AtomicNumber": "11",
    "ElementName": "Sodium",
    "Symbol": "Na",
    "AtomicWeight": "22.98976928",
    "Period": "3",
    "Group": "1",
    "IonicRadius": "1",
    "AtomicRadius": "2.2",
    "Electronegativity": "0.93",
    "FirstIonizationPotential": "5.1391",
    "Density": "0.971",
    "MeltingPoint": "371.15",
    "BoilingPoint": "1156",
    "Isotopes": "7",
    "SpecificHeatCapacity": "1.228",
    "ElectronConfiguration": "[Ne] 3s1",
    "DisplayRow": "3",
    "DisplayColumn": "1",
    "Id": 11,
    "Guid": "011fb1b4-ce71-4dd2-9f48-039f9fe84286",
    "TimeAdded": "2023-09-21T04:51:35.566783+00:00",
    "UserAddedId": 1,
    "TimeModified": "2023-09-21T04:51:35.566783+00:00",
    "UserModifiedId": 1,
    "IsActive": true
  },
  {
    "AtomicNumber": "12",
    "ElementName": "Magnesium",
    "Symbol": "Mg",
    "AtomicWeight": "24.305",
    "Period": "3",
    "Group": "2",
    "IonicRadius": "0.72",
    "AtomicRadius": "1.7",
    "Electronegativity": "1.31",
    "FirstIonizationPotential": "7.6462",
    "Density": "1.738",
    "MeltingPoint": "923.15",
    "BoilingPoint": "1363",
    "Isotopes": "8",
    "SpecificHeatCapacity": "1.023",
    "ElectronConfiguration": "[Ne] 3s2",
    "DisplayRow": "3",
    "DisplayColumn": "2",
    "Id": 12,
    "Guid": "a1235df2-2e58-48c5-a37c-83e689a14776",
    "TimeAdded": "2023-09-21T04:51:35.566783+00:00",
    "UserAddedId": 1,
    "TimeModified": "2023-09-21T04:51:35.566783+00:00",
    "UserModifiedId": 1,
    "IsActive": true
  },
  {
    "AtomicNumber": "13",
    "ElementName": "Aluminum",
    "Symbol": "Al",
    "AtomicWeight": "26.9815386",
    "Period": "3",
    "Group": "13",
    "IonicRadius": "0.54",
    "AtomicRadius": "1.8",
    "Electronegativity": "1.61",
    "FirstIonizationPotential": "5.9858",
    "Density": "2.698",
    "MeltingPoint": "933.4",
    "BoilingPoint": "2792",
    "Isotopes": "8",
    "SpecificHeatCapacity": "0.897",
    "ElectronConfiguration": "[Ne] 3s2 3p1",
    "DisplayRow": "3",
    "DisplayColumn": "13",
    "Id": 13,
    "Guid": "4d15b180-51e9-44f5-8b9a-0e1b947be456",
    "TimeAdded": "2023-09-21T04:51:35.566783+00:00",
    "UserAddedId": 1,
    "TimeModified": "2023-09-21T04:51:35.566783+00:00",
    "UserModifiedId": 1,
    "IsActive": true
  },
  {
    "AtomicNumber": "14",
    "ElementName": "Silicon",
    "Symbol": "Si",
    "AtomicWeight": "28.0855",
    "Period": "3",
    "Group": "14",
    "IonicRadius": "0.4",
    "AtomicRadius": "1.5",
    "Electronegativity": "1.9",
    "FirstIonizationPotential": "8.1517",
    "Density": "2.3296",
    "MeltingPoint": "1683.15",
    "BoilingPoint": "3538",
    "Isotopes": "8",
    "SpecificHeatCapacity": "0.705",
    "ElectronConfiguration": "[Ne] 3s2 3p2",
    "DisplayRow": "3",
    "DisplayColumn": "14",
    "Id": 14,
    "Guid": "b815b23e-8cb3-4bcf-9e54-2ba8cbad731e",
    "TimeAdded": "2023-09-21T04:51:35.566783+00:00",
    "UserAddedId": 1,
    "TimeModified": "2023-09-21T04:51:35.566783+00:00",
    "UserModifiedId": 1,
    "IsActive": true
  },
  {
    "AtomicNumber": "15",
    "ElementName": "Phosphorus",
    "Symbol": "P",
    "AtomicWeight": "30.973762",
    "Period": "3",
    "Group": "15",
    "IonicRadius": "0.38",
    "AtomicRadius": "1.2",
    "Electronegativity": "2.19",
    "FirstIonizationPotential": "10.4867",
    "Density": "1.82",
    "MeltingPoint": "317.25",
    "BoilingPoint": "553",
    "Isotopes": "7",
    "SpecificHeatCapacity": "0.769",
    "ElectronConfiguration": "[Ne] 3s2 3p3",
    "DisplayRow": "3",
    "DisplayColumn": "15",
    "Id": 15,
    "Guid": "fdf47fe4-bed0-438b-870f-0be2b7b8384f",
    "TimeAdded": "2023-09-21T04:51:35.566783+00:00",
    "UserAddedId": 1,
    "TimeModified": "2023-09-21T04:51:35.566783+00:00",
    "UserModifiedId": 1,
    "IsActive": true
  },
  {
    "AtomicNumber": "16",
    "ElementName": "Sulfur",
    "Symbol": "S",
    "AtomicWeight": "32.065",
    "Period": "3",
    "Group": "16",
    "IonicRadius": "0.37",
    "AtomicRadius": "1.1",
    "Electronegativity": "2.58",
    "FirstIonizationPotential": "10.36",
    "Density": "2.067",
    "MeltingPoint": "388.51",
    "BoilingPoint": "717.8",
    "Isotopes": "10",
    "SpecificHeatCapacity": "0.71",
    "ElectronConfiguration": "[Ne] 3s2 3p4",
    "DisplayRow": "3",
    "DisplayColumn": "16",
    "Id": 16,
    "Guid": "49cfc85f-b4cd-4406-a9ec-10969e8a43c6",
    "TimeAdded": "2023-09-21T04:51:35.566783+00:00",
    "UserAddedId": 1,
    "TimeModified": "2023-09-21T04:51:35.566783+00:00",
    "UserModifiedId": 1,
    "IsActive": true
  },
  {
    "AtomicNumber": "17",
    "ElementName": "Chlorine",
    "Symbol": "Cl",
    "AtomicWeight": "35.453",
    "Period": "3",
    "Group": "17",
    "IonicRadius": "1.8",
    "AtomicRadius": "0.97",
    "Electronegativity": "3.16",
    "FirstIonizationPotential": "12.9676",
    "Density": "0.003214",
    "MeltingPoint": "172.31",
    "BoilingPoint": "239.11",
    "Isotopes": "11",
    "SpecificHeatCapacity": "0.479",
    "ElectronConfiguration": "[Ne] 3s2 3p5",
    "DisplayRow": "3",
    "DisplayColumn": "17",
    "Id": 17,
    "Guid": "21198bf4-e881-4048-b15e-4392addca50d",
    "TimeAdded": "2023-09-21T04:51:35.566783+00:00",
    "UserAddedId": 1,
    "TimeModified": "2023-09-21T04:51:35.566783+00:00",
    "UserModifiedId": 1,
    "IsActive": true
  },
  {
    "AtomicNumber": "18",
    "ElementName": "Argon",
    "Symbol": "Ar",
    "AtomicWeight": "39.948",
    "Period": "3",
    "Group": "18",
    "IonicRadius": "",
    "AtomicRadius": "0.88",
    "Electronegativity": "",
    "FirstIonizationPotential": "15.7596",
    "Density": "0.0017837",
    "MeltingPoint": "83.96",
    "BoilingPoint": "87.3",
    "Isotopes": "8",
    "SpecificHeatCapacity": "0.52",
    "ElectronConfiguration": "[Ne] 3s2 3p6",
    "DisplayRow": "3",
    "DisplayColumn": "18",
    "Id": 18,
    "Guid": "c8754f73-7680-45ba-b6e7-7c7502b80a7f",
    "TimeAdded": "2023-09-21T04:51:35.566783+00:00",
    "UserAddedId": 1,
    "TimeModified": "2023-09-21T04:51:35.566783+00:00",
    "UserModifiedId": 1,
    "IsActive": true
  },
  {
    "AtomicNumber": "19",
    "ElementName": "Potassium",
    "Symbol": "K",
    "AtomicWeight": "39.0983",
    "Period": "4",
    "Group": "1",
    "IonicRadius": "1.4",
    "AtomicRadius": "2.8",
    "Electronegativity": "0.82",
    "FirstIonizationPotential": "4.3407",
    "Density": "0.862",
    "MeltingPoint": "336.5",
    "BoilingPoint": "1032",
    "Isotopes": "10",
    "SpecificHeatCapacity": "0.757",
    "ElectronConfiguration": "[Ar] 4s1",
    "DisplayRow": "4",
    "DisplayColumn": "1",
    "Id": 19,
    "Guid": "3d7c5aaa-4862-4da2-8ed5-798842d39ecf",
    "TimeAdded": "2023-09-21T04:51:35.566783+00:00",
    "UserAddedId": 1,
    "TimeModified": "2023-09-21T04:51:35.566783+00:00",
    "UserModifiedId": 1,
    "IsActive": true
  },
  {
    "AtomicNumber": "20",
    "ElementName": "Calcium",
    "Symbol": "Ca",
    "AtomicWeight": "40.078",
    "Period": "4",
    "Group": "2",
    "IonicRadius": "0.99",
    "AtomicRadius": "2.2",
    "Electronegativity": "1",
    "FirstIonizationPotential": "6.1132",
    "Density": "1.54",
    "MeltingPoint": "1112.15",
    "BoilingPoint": "1757",
    "Isotopes": "14",
    "SpecificHeatCapacity": "0.647",
    "ElectronConfiguration": "[Ar] 4s2",
    "DisplayRow": "4",
    "DisplayColumn": "2",
    "Id": 20,
    "Guid": "f48b0a94-57c2-4c82-8754-b1f82de20f54",
    "TimeAdded": "2023-09-21T04:51:35.566783+00:00",
    "UserAddedId": 1,
    "TimeModified": "2023-09-21T04:51:35.566783+00:00",
    "UserModifiedId": 1,
    "IsActive": true
  },
  {
    "AtomicNumber": "21",
    "ElementName": "Scandium",
    "Symbol": "Sc",
    "AtomicWeight": "44.955912",
    "Period": "4",
    "Group": "3",
    "IonicRadius": "0.75",
    "AtomicRadius": "2.1",
    "Electronegativity": "1.36",
    "FirstIonizationPotential": "6.5615",
    "Density": "2.989",
    "MeltingPoint": "1812.15",
    "BoilingPoint": "3109",
    "Isotopes": "15",
    "SpecificHeatCapacity": "0.568",
    "ElectronConfiguration": "[Ar] 3d1 4s2",
    "DisplayRow": "4",
    "DisplayColumn": "3",
    "Id": 21,
    "Guid": "7de0c9f4-f155-45bd-891d-e8e54dd8160c",
    "TimeAdded": "2023-09-21T04:51:35.566783+00:00",
    "UserAddedId": 1,
    "TimeModified": "2023-09-21T04:51:35.566783+00:00",
    "UserModifiedId": 1,
    "IsActive": true
  },
  {
    "AtomicNumber": "22",
    "ElementName": "Titanium",
    "Symbol": "Ti",
    "AtomicWeight": "47.867",
    "Period": "4",
    "Group": "4",
    "IonicRadius": "0.61",
    "AtomicRadius": "2",
    "Electronegativity": "1.54",
    "FirstIonizationPotential": "6.8281",
    "Density": "4.54",
    "MeltingPoint": "1933.15",
    "BoilingPoint": "3560",
    "Isotopes": "9",
    "SpecificHeatCapacity": "0.523",
    "ElectronConfiguration": "[Ar] 3d2 4s2",
    "DisplayRow": "4",
    "DisplayColumn": "4",
    "Id": 22,
    "Guid": "e5284f84-4cd8-449e-ad73-9ed4719944f9",
    "TimeAdded": "2023-09-21T04:51:35.566783+00:00",
    "UserAddedId": 1,
    "TimeModified": "2023-09-21T04:51:35.566783+00:00",
    "UserModifiedId": 1,
    "IsActive": true
  },
  {
    "AtomicNumber": "23",
    "ElementName": "Vanadium",
    "Symbol": "V",
    "AtomicWeight": "50.9415",
    "Period": "4",
    "Group": "5",
    "IonicRadius": "0.59",
    "AtomicRadius": "1.9",
    "Electronegativity": "1.63",
    "FirstIonizationPotential": "6.7462",
    "Density": "6.11",
    "MeltingPoint": "2175.15",
    "BoilingPoint": "3680",
    "Isotopes": "9",
    "SpecificHeatCapacity": "0.489",
    "ElectronConfiguration": "[Ar] 3d3 4s2",
    "DisplayRow": "4",
    "DisplayColumn": "5",
    "Id": 23,
    "Guid": "490ed6e9-d6d0-4d7d-9535-dd1a6b1447c0",
    "TimeAdded": "2023-09-21T04:51:35.566783+00:00",
    "UserAddedId": 1,
    "TimeModified": "2023-09-21T04:51:35.566783+00:00",
    "UserModifiedId": 1,
    "IsActive": true
  },
  {
    "AtomicNumber": "24",
    "ElementName": "Chromium",
    "Symbol": "Cr",
    "AtomicWeight": "51.9961",
    "Period": "4",
    "Group": "6",
    "IonicRadius": "0.52",
    "AtomicRadius": "1.9",
    "Electronegativity": "1.66",
    "FirstIonizationPotential": "6.7665",
    "Density": "7.15",
    "MeltingPoint": "2130.15",
    "BoilingPoint": "2944",
    "Isotopes": "9",
    "SpecificHeatCapacity": "0.449",
    "ElectronConfiguration": "[Ar] 3d5 4s1",
    "DisplayRow": "4",
    "DisplayColumn": "6",
    "Id": 24,
    "Guid": "8c9d5a16-73ec-4369-9d18-dd00cd403444",
    "TimeAdded": "2023-09-21T04:51:35.566783+00:00",
    "UserAddedId": 1,
    "TimeModified": "2023-09-21T04:51:35.566783+00:00",
    "UserModifiedId": 1,
    "IsActive": true
  },
  {
    "AtomicNumber": "25",
    "ElementName": "Manganese",
    "Symbol": "Mn",
    "AtomicWeight": "54.938045",
    "Period": "4",
    "Group": "7",
    "IonicRadius": "0.46",
    "AtomicRadius": "1.8",
    "Electronegativity": "1.55",
    "FirstIonizationPotential": "7.434",
    "Density": "7.44",
    "MeltingPoint": "1519.15",
    "BoilingPoint": "2334",
    "Isotopes": "11",
    "SpecificHeatCapacity": "0.479",
    "ElectronConfiguration": "[Ar] 3d5 4s2",
    "DisplayRow": "4",
    "DisplayColumn": "7",
    "Id": 25,
    "Guid": "bfeeb4a2-57f6-43f6-9799-59ce69a75d97",
    "TimeAdded": "2023-09-21T04:51:35.566783+00:00",
    "UserAddedId": 1,
    "TimeModified": "2023-09-21T04:51:35.566783+00:00",
    "UserModifiedId": 1,
    "IsActive": true
  },
  {
    "AtomicNumber": "26",
    "ElementName": "Iron",
    "Symbol": "Fe",
    "AtomicWeight": "55.845",
    "Period": "4",
    "Group": "8",
    "IonicRadius": "0.65",
    "AtomicRadius": "1.7",
    "Electronegativity": "1.83",
    "FirstIonizationPotential": "7.9024",
    "Density": "7.874",
    "MeltingPoint": "1808.15",
    "BoilingPoint": "3134",
    "Isotopes": "10",
    "SpecificHeatCapacity": "0.449",
    "ElectronConfiguration": "[Ar] 3d6 4s2",
    "DisplayRow": "4",
    "DisplayColumn": "8",
    "Id": 26,
    "Guid": "06c550dd-37be-4253-b64f-335c8d0dcbee",
    "TimeAdded": "2023-09-21T04:51:35.566783+00:00",
    "UserAddedId": 1,
    "TimeModified": "2023-09-21T04:51:35.566783+00:00",
    "UserModifiedId": 1,
    "IsActive": true
  },
  {
    "AtomicNumber": "27",
    "ElementName": "Cobalt",
    "Symbol": "Co",
    "AtomicWeight": "58.933195",
    "Period": "4",
    "Group": "9",
    "IonicRadius": "0.75",
    "AtomicRadius": "1.7",
    "Electronegativity": "1.88",
    "FirstIonizationPotential": "7.881",
    "Density": "8.86",
    "MeltingPoint": "1768.15",
    "BoilingPoint": "3200",
    "Isotopes": "14",
    "SpecificHeatCapacity": "0.421",
    "ElectronConfiguration": "[Ar] 3d7 4s2",
    "DisplayRow": "4",
    "DisplayColumn": "9",
    "Id": 27,
    "Guid": "66f2eb11-9002-4d2e-999a-a3ea5ec7893e",
    "TimeAdded": "2023-09-21T04:51:35.566783+00:00",
    "UserAddedId": 1,
    "TimeModified": "2023-09-21T04:51:35.566783+00:00",
    "UserModifiedId": 1,
    "IsActive": true
  },
  {
    "AtomicNumber": "28",
    "ElementName": "Nickel",
    "Symbol": "Ni",
    "AtomicWeight": "58.6934",
    "Period": "4",
    "Group": "10",
    "IonicRadius": "0.69",
    "AtomicRadius": "1.6",
    "Electronegativity": "1.91",
    "FirstIonizationPotential": "7.6398",
    "Density": "8.912",
    "MeltingPoint": "1726.15",
    "BoilingPoint": "3186",
    "Isotopes": "11",
    "SpecificHeatCapacity": "0.444",
    "ElectronConfiguration": "[Ar] 3d8 4s2",
    "DisplayRow": "4",
    "DisplayColumn": "10",
    "Id": 28,
    "Guid": "688b338e-084d-4640-a9cb-2bd727910528",
    "TimeAdded": "2023-09-21T04:51:35.566783+00:00",
    "UserAddedId": 1,
    "TimeModified": "2023-09-21T04:51:35.566783+00:00",
    "UserModifiedId": 1,
    "IsActive": true
  },
  {
    "AtomicNumber": "29",
    "ElementName": "Copper",
    "Symbol": "Cu",
    "AtomicWeight": "63.546",
    "Period": "4",
    "Group": "11",
    "IonicRadius": "0.73",
    "AtomicRadius": "1.6",
    "Electronegativity": "1.9",
    "FirstIonizationPotential": "7.7264",
    "Density": "8.96",
    "MeltingPoint": "1357.75",
    "BoilingPoint": "2835",
    "Isotopes": "11",
    "SpecificHeatCapacity": "0.385",
    "ElectronConfiguration": "[Ar] 3d10 4s1",
    "DisplayRow": "4",
    "DisplayColumn": "11",
    "Id": 29,
    "Guid": "8f9fa04d-3b73-4be5-b1a5-f7f9517329e7",
    "TimeAdded": "2023-09-21T04:51:35.566783+00:00",
    "UserAddedId": 1,
    "TimeModified": "2023-09-21T04:51:35.566783+00:00",
    "UserModifiedId": 1,
    "IsActive": true
  },
  {
    "AtomicNumber": "30",
    "ElementName": "Zinc",
    "Symbol": "Zn",
    "AtomicWeight": "65.38",
    "Period": "4",
    "Group": "12",
    "IonicRadius": "0.74",
    "AtomicRadius": "1.5",
    "Electronegativity": "1.65",
    "FirstIonizationPotential": "9.3942",
    "Density": "7.134",
    "MeltingPoint": "692.88",
    "BoilingPoint": "1180",
    "Isotopes": "15",
    "SpecificHeatCapacity": "0.388",
    "ElectronConfiguration": "[Ar] 3d10 4s2",
    "DisplayRow": "4",
    "DisplayColumn": "12",
    "Id": 30,
    "Guid": "3db926ba-bda0-4ee1-9a61-78cb5ccc007b",
    "TimeAdded": "2023-09-21T04:51:35.566783+00:00",
    "UserAddedId": 1,
    "TimeModified": "2023-09-21T04:51:35.566783+00:00",
    "UserModifiedId": 1,
    "IsActive": true
  },
  {
    "AtomicNumber": "31",
    "ElementName": "Gallium",
    "Symbol": "Ga",
    "AtomicWeight": "69.723",
    "Period": "4",
    "Group": "13",
    "IonicRadius": "0.62",
    "AtomicRadius": "1.8",
    "Electronegativity": "1.81",
    "FirstIonizationPotential": "5.9993",
    "Density": "5.907",
    "MeltingPoint": "302.91",
    "BoilingPoint": "2477",
    "Isotopes": "14",
    "SpecificHeatCapacity": "0.371",
    "ElectronConfiguration": "[Ar] 3d10 4s2 4p1",
    "DisplayRow": "4",
    "DisplayColumn": "13",
    "Id": 31,
    "Guid": "3f7f16e1-2335-4008-9826-464a54de0735",
    "TimeAdded": "2023-09-21T04:51:35.566783+00:00",
    "UserAddedId": 1,
    "TimeModified": "2023-09-21T04:51:35.566783+00:00",
    "UserModifiedId": 1,
    "IsActive": true
  },
  {
    "AtomicNumber": "32",
    "ElementName": "Germanium",
    "Symbol": "Ge",
    "AtomicWeight": "72.64",
    "Period": "4",
    "Group": "14",
    "IonicRadius": "0.53",
    "AtomicRadius": "1.5",
    "Electronegativity": "2.01",
    "FirstIonizationPotential": "7.8994",
    "Density": "5.323",
    "MeltingPoint": "1211.45",
    "BoilingPoint": "3106",
    "Isotopes": "17",
    "SpecificHeatCapacity": "0.32",
    "ElectronConfiguration": "[Ar] 3d10 4s2 4p2",
    "DisplayRow": "4",
    "DisplayColumn": "14",
    "Id": 32,
    "Guid": "58463c08-f261-4d0c-b12f-20878f8d69b1",
    "TimeAdded": "2023-09-21T04:51:35.567782+00:00",
    "UserAddedId": 1,
    "TimeModified": "2023-09-21T04:51:35.567782+00:00",
    "UserModifiedId": 1,
    "IsActive": true
  },
  {
    "AtomicNumber": "33",
    "ElementName": "Arsenic",
    "Symbol": "As",
    "AtomicWeight": "74.9216",
    "Period": "4",
    "Group": "15",
    "IonicRadius": "0.58",
    "AtomicRadius": "1.3",
    "Electronegativity": "2.18",
    "FirstIonizationPotential": "9.7886",
    "Density": "5.776",
    "MeltingPoint": "1090.15",
    "BoilingPoint": "887",
    "Isotopes": "14",
    "SpecificHeatCapacity": "0.329",
    "ElectronConfiguration": "[Ar] 3d10 4s2 4p3",
    "DisplayRow": "4",
    "DisplayColumn": "15",
    "Id": 33,
    "Guid": "0bc7c0f8-fb7b-43ba-98c7-b241188f9697",
    "TimeAdded": "2023-09-21T04:51:35.567782+00:00",
    "UserAddedId": 1,
    "TimeModified": "2023-09-21T04:51:35.567782+00:00",
    "UserModifiedId": 1,
    "IsActive": true
  },
  {
    "AtomicNumber": "34",
    "ElementName": "Selenium",
    "Symbol": "Se",
    "AtomicWeight": "78.96",
    "Period": "4",
    "Group": "16",
    "IonicRadius": "0.5",
    "AtomicRadius": "1.2",
    "Electronegativity": "2.55",
    "FirstIonizationPotential": "9.7524",
    "Density": "4.809",
    "MeltingPoint": "494.15",
    "BoilingPoint": "958",
    "Isotopes": "20",
    "SpecificHeatCapacity": "0.321",
    "ElectronConfiguration": "[Ar] 3d10 4s2 4p4",
    "DisplayRow": "4",
    "DisplayColumn": "16",
    "Id": 34,
    "Guid": "762e94fb-5a37-4555-8a7d-0a56e0c6d42f",
    "TimeAdded": "2023-09-21T04:51:35.567782+00:00",
    "UserAddedId": 1,
    "TimeModified": "2023-09-21T04:51:35.567782+00:00",
    "UserModifiedId": 1,
    "IsActive": true
  },
  {
    "AtomicNumber": "35",
    "ElementName": "Bromine",
    "Symbol": "Br",
    "AtomicWeight": "79.904",
    "Period": "4",
    "Group": "17",
    "IonicRadius": "2",
    "AtomicRadius": "1.1",
    "Electronegativity": "2.96",
    "FirstIonizationPotential": "11.8138",
    "Density": "3.122",
    "MeltingPoint": "266.05",
    "BoilingPoint": "332",
    "Isotopes": "19",
    "SpecificHeatCapacity": "0.474",
    "ElectronConfiguration": "[Ar] 3d10 4s2 4p5",
    "DisplayRow": "4",
    "DisplayColumn": "17",
    "Id": 35,
    "Guid": "9a775c11-425f-49f9-bb24-65386dfcca8f",
    "TimeAdded": "2023-09-21T04:51:35.567782+00:00",
    "UserAddedId": 1,
    "TimeModified": "2023-09-21T04:51:35.567782+00:00",
    "UserModifiedId": 1,
    "IsActive": true
  },
  {
    "AtomicNumber": "36",
    "ElementName": "Krypton",
    "Symbol": "Kr",
    "AtomicWeight": "83.798",
    "Period": "4",
    "Group": "18",
    "IonicRadius": "",
    "AtomicRadius": "1",
    "Electronegativity": "",
    "FirstIonizationPotential": "13.9996",
    "Density": "0.003733",
    "MeltingPoint": "115.93",
    "BoilingPoint": "119.93",
    "Isotopes": "23",
    "SpecificHeatCapacity": "0.248",
    "ElectronConfiguration": "[Ar] 3d10 4s2 4p6",
    "DisplayRow": "4",
    "DisplayColumn": "18",
    "Id": 36,
    "Guid": "c4740240-a9c8-4f75-b69f-fa95558a5f43",
    "TimeAdded": "2023-09-21T04:51:35.567782+00:00",
    "UserAddedId": 1,
    "TimeModified": "2023-09-21T04:51:35.567782+00:00",
    "UserModifiedId": 1,
    "IsActive": true
  },
  {
    "AtomicNumber": "37",
    "ElementName": "Rubidium",
    "Symbol": "Rb",
    "AtomicWeight": "85.4678",
    "Period": "5",
    "Group": "1",
    "IonicRadius": "1.5",
    "AtomicRadius": "3",
    "Electronegativity": "0.82",
    "FirstIonizationPotential": "4.1771",
    "Density": "1.532",
    "MeltingPoint": "312.79",
    "BoilingPoint": "961",
    "Isotopes": "20",
    "SpecificHeatCapacity": "0.363",
    "ElectronConfiguration": "[Kr] 5s1",
    "DisplayRow": "5",
    "DisplayColumn": "1",
    "Id": 37,
    "Guid": "8714ae4c-a49b-40d0-84d0-468d08027722",
    "TimeAdded": "2023-09-21T04:51:35.567782+00:00",
    "UserAddedId": 1,
    "TimeModified": "2023-09-21T04:51:35.567782+00:00",
    "UserModifiedId": 1,
    "IsActive": true
  },
  {
    "AtomicNumber": "38",
    "ElementName": "Strontium",
    "Symbol": "Sr",
    "AtomicWeight": "87.62",
    "Period": "5",
    "Group": "2",
    "IonicRadius": "1.1",
    "AtomicRadius": "2.5",
    "Electronegativity": "0.95",
    "FirstIonizationPotential": "5.6949",
    "Density": "2.64",
    "MeltingPoint": "1042.15",
    "BoilingPoint": "1655",
    "Isotopes": "18",
    "SpecificHeatCapacity": "0.301",
    "ElectronConfiguration": "[Kr] 5s2",
    "DisplayRow": "5",
    "DisplayColumn": "2",
    "Id": 38,
    "Guid": "a65933b6-d7a6-4c08-ac91-105397a0d537",
    "TimeAdded": "2023-09-21T04:51:35.567782+00:00",
    "UserAddedId": 1,
    "TimeModified": "2023-09-21T04:51:35.567782+00:00",
    "UserModifiedId": 1,
    "IsActive": true
  },
  {
    "AtomicNumber": "39",
    "ElementName": "Yttrium",
    "Symbol": "Y",
    "AtomicWeight": "88.90585",
    "Period": "5",
    "Group": "3",
    "IonicRadius": "0.9",
    "AtomicRadius": "2.3",
    "Electronegativity": "1.22",
    "FirstIonizationPotential": "6.2173",
    "Density": "4.469",
    "MeltingPoint": "1799.15",
    "BoilingPoint": "3609",
    "Isotopes": "21",
    "SpecificHeatCapacity": "0.298",
    "ElectronConfiguration": "[Kr] 4d1 5s2",
    "DisplayRow": "5",
    "DisplayColumn": "3",
    "Id": 39,
    "Guid": "27c0ab53-d1c7-46ef-9d0b-02c2d4b74991",
    "TimeAdded": "2023-09-21T04:51:35.567782+00:00",
    "UserAddedId": 1,
    "TimeModified": "2023-09-21T04:51:35.567782+00:00",
    "UserModifiedId": 1,
    "IsActive": true
  },
  {
    "AtomicNumber": "40",
    "ElementName": "Zirconium",
    "Symbol": "Zr",
    "AtomicWeight": "91.224",
    "Period": "5",
    "Group": "4",
    "IonicRadius": "0.72",
    "AtomicRadius": "2.2",
    "Electronegativity": "1.33",
    "FirstIonizationPotential": "6.6339",
    "Density": "6.506",
    "MeltingPoint": "2125.15",
    "BoilingPoint": "4682",
    "Isotopes": "20",
    "SpecificHeatCapacity": "0.278",
    "ElectronConfiguration": "[Kr] 4d2 5s2",
    "DisplayRow": "5",
    "DisplayColumn": "4",
    "Id": 40,
    "Guid": "814459bb-e6a5-43b6-b59a-2b8c04b50d33",
    "TimeAdded": "2023-09-21T04:51:35.567782+00:00",
    "UserAddedId": 1,
    "TimeModified": "2023-09-21T04:51:35.567782+00:00",
    "UserModifiedId": 1,
    "IsActive": true
  },
  {
    "AtomicNumber": "41",
    "ElementName": "Niobium",
    "Symbol": "Nb",
    "AtomicWeight": "92.90638",
    "Period": "5",
    "Group": "5",
    "IonicRadius": "0.69",
    "AtomicRadius": "2.1",
    "Electronegativity": "1.6",
    "FirstIonizationPotential": "6.7589",
    "Density": "8.57",
    "MeltingPoint": "2741.15",
    "BoilingPoint": "5017",
    "Isotopes": "24",
    "SpecificHeatCapacity": "0.265",
    "ElectronConfiguration": "[Kr] 4d4 5s1",
    "DisplayRow": "5",
    "DisplayColumn": "5",
    "Id": 41,
    "Guid": "67d4a9ff-2889-4813-8c3e-46166e6f95a3",
    "TimeAdded": "2023-09-21T04:51:35.567782+00:00",
    "UserAddedId": 1,
    "TimeModified": "2023-09-21T04:51:35.567782+00:00",
    "UserModifiedId": 1,
    "IsActive": true
  },
  {
    "AtomicNumber": "42",
    "ElementName": "Molybdenum",
    "Symbol": "Mo",
    "AtomicWeight": "95.96",
    "Period": "5",
    "Group": "6",
    "IonicRadius": "0.65",
    "AtomicRadius": "2",
    "Electronegativity": "2.16",
    "FirstIonizationPotential": "7.0924",
    "Density": "10.22",
    "MeltingPoint": "2890.15",
    "BoilingPoint": "4912",
    "Isotopes": "20",
    "SpecificHeatCapacity": "0.251",
    "ElectronConfiguration": "[Kr] 4d5 5s1",
    "DisplayRow": "5",
    "DisplayColumn": "6",
    "Id": 42,
    "Guid": "5d156707-f910-40a9-acea-230c3d49ec38",
    "TimeAdded": "2023-09-21T04:51:35.567782+00:00",
    "UserAddedId": 1,
    "TimeModified": "2023-09-21T04:51:35.567782+00:00",
    "UserModifiedId": 1,
    "IsActive": true
  },
  {
    "AtomicNumber": "43",
    "ElementName": "Technetium",
    "Symbol": "Tc",
    "AtomicWeight": "98",
    "Period": "5",
    "Group": "7",
    "IonicRadius": "0.56",
    "AtomicRadius": "2",
    "Electronegativity": "1.9",
    "FirstIonizationPotential": "7.28",
    "Density": "11.5",
    "MeltingPoint": "2473.15",
    "BoilingPoint": "5150",
    "Isotopes": "23",
    "SpecificHeatCapacity": "",
    "ElectronConfiguration": "[Kr] 4d5 5s2",
    "DisplayRow": "5",
    "DisplayColumn": "7",
    "Id": 43,
    "Guid": "fe135b66-fd63-4e1e-bed0-01a1f2eda801",
    "TimeAdded": "2023-09-21T04:51:35.567782+00:00",
    "UserAddedId": 1,
    "TimeModified": "2023-09-21T04:51:35.567782+00:00",
    "UserModifiedId": 1,
    "IsActive": true
  },
  {
    "AtomicNumber": "44",
    "ElementName": "Ruthenium",
    "Symbol": "Ru",
    "AtomicWeight": "101.07",
    "Period": "5",
    "Group": "8",
    "IonicRadius": "0.68",
    "AtomicRadius": "1.9",
    "Electronegativity": "2.2",
    "FirstIonizationPotential": "7.3605",
    "Density": "12.37",
    "MeltingPoint": "2523.15",
    "BoilingPoint": "4423",
    "Isotopes": "16",
    "SpecificHeatCapacity": "0.238",
    "ElectronConfiguration": "[Kr] 4d7 5s1",
    "DisplayRow": "5",
    "DisplayColumn": "8",
    "Id": 44,
    "Guid": "ac69c66a-e0ab-4a8e-aff1-795f8fb440e8",
    "TimeAdded": "2023-09-21T04:51:35.567782+00:00",
    "UserAddedId": 1,
    "TimeModified": "2023-09-21T04:51:35.567782+00:00",
    "UserModifiedId": 1,
    "IsActive": true
  },
  {
    "AtomicNumber": "45",
    "ElementName": "Rhodium",
    "Symbol": "Rh",
    "AtomicWeight": "102.9055",
    "Period": "5",
    "Group": "9",
    "IonicRadius": "0.68",
    "AtomicRadius": "1.8",
    "Electronegativity": "2.28",
    "FirstIonizationPotential": "7.4589",
    "Density": "12.41",
    "MeltingPoint": "2239.15",
    "BoilingPoint": "3968",
    "Isotopes": "20",
    "SpecificHeatCapacity": "0.243",
    "ElectronConfiguration": "[Kr] 4d8 5s1",
    "DisplayRow": "5",
    "DisplayColumn": "9",
    "Id": 45,
    "Guid": "af950e10-93b7-4050-bb31-41ebaefdaff6",
    "TimeAdded": "2023-09-21T04:51:35.567782+00:00",
    "UserAddedId": 1,
    "TimeModified": "2023-09-21T04:51:35.567782+00:00",
    "UserModifiedId": 1,
    "IsActive": true
  },
  {
    "AtomicNumber": "46",
    "ElementName": "Palladium",
    "Symbol": "Pd",
    "AtomicWeight": "106.42",
    "Period": "5",
    "Group": "10",
    "IonicRadius": "0.86",
    "AtomicRadius": "1.8",
    "Electronegativity": "2.2",
    "FirstIonizationPotential": "8.3369",
    "Density": "12.02",
    "MeltingPoint": "1825.15",
    "BoilingPoint": "3236",
    "Isotopes": "21",
    "SpecificHeatCapacity": "0.244",
    "ElectronConfiguration": "[Kr] 4d10",
    "DisplayRow": "5",
    "DisplayColumn": "10",
    "Id": 46,
    "Guid": "51e75951-c6f7-4766-834f-58707a54c915",
    "TimeAdded": "2023-09-21T04:51:35.567782+00:00",
    "UserAddedId": 1,
    "TimeModified": "2023-09-21T04:51:35.567782+00:00",
    "UserModifiedId": 1,
    "IsActive": true
  },
  {
    "AtomicNumber": "47",
    "ElementName": "Silver",
    "Symbol": "Ag",
    "AtomicWeight": "107.8682",
    "Period": "5",
    "Group": "11",
    "IonicRadius": "1.3",
    "AtomicRadius": "1.8",
    "Electronegativity": "1.93",
    "FirstIonizationPotential": "7.5762",
    "Density": "10.501",
    "MeltingPoint": "1234.15",
    "BoilingPoint": "2435",
    "Isotopes": "27",
    "SpecificHeatCapacity": "0.235",
    "ElectronConfiguration": "[Kr] 4d10 5s1",
    "DisplayRow": "5",
    "DisplayColumn": "11",
    "Id": 47,
    "Guid": "07f87993-bdae-4887-826e-918f2432c630",
    "TimeAdded": "2023-09-21T04:51:35.567782+00:00",
    "UserAddedId": 1,
    "TimeModified": "2023-09-21T04:51:35.567782+00:00",
    "UserModifiedId": 1,
    "IsActive": true
  },
  {
    "AtomicNumber": "48",
    "ElementName": "Cadmium",
    "Symbol": "Cd",
    "AtomicWeight": "112.411",
    "Period": "5",
    "Group": "12",
    "IonicRadius": "0.97",
    "AtomicRadius": "1.7",
    "Electronegativity": "1.69",
    "FirstIonizationPotential": "8.9938",
    "Density": "8.69",
    "MeltingPoint": "594.33",
    "BoilingPoint": "1040",
    "Isotopes": "22",
    "SpecificHeatCapacity": "0.232",
    "ElectronConfiguration": "[Kr] 4d10 5s2",
    "DisplayRow": "5",
    "DisplayColumn": "12",
    "Id": 48,
    "Guid": "b50e3437-29c4-4e06-b1c9-dfb71c009af1",
    "TimeAdded": "2023-09-21T04:51:35.567782+00:00",
    "UserAddedId": 1,
    "TimeModified": "2023-09-21T04:51:35.567782+00:00",
    "UserModifiedId": 1,
    "IsActive": true
  },
  {
    "AtomicNumber": "49",
    "ElementName": "Indium",
    "Symbol": "In",
    "AtomicWeight": "114.818",
    "Period": "5",
    "Group": "13",
    "IonicRadius": "0.8",
    "AtomicRadius": "2",
    "Electronegativity": "1.78",
    "FirstIonizationPotential": "5.7864",
    "Density": "7.31",
    "MeltingPoint": "429.91",
    "BoilingPoint": "2345",
    "Isotopes": "34",
    "SpecificHeatCapacity": "0.233",
    "ElectronConfiguration": "[Kr] 4d10 5s2 5p1",
    "DisplayRow": "5",
    "DisplayColumn": "13",
    "Id": 49,
    "Guid": "499f9a9d-2b5a-4d53-893b-20193e77d0fc",
    "TimeAdded": "2023-09-21T04:51:35.567782+00:00",
    "UserAddedId": 1,
    "TimeModified": "2023-09-21T04:51:35.567782+00:00",
    "UserModifiedId": 1,
    "IsActive": true
  },
  {
    "AtomicNumber": "50",
    "ElementName": "Tin",
    "Symbol": "Sn",
    "AtomicWeight": "118.71",
    "Period": "5",
    "Group": "14",
    "IonicRadius": "0.69",
    "AtomicRadius": "1.7",
    "Electronegativity": "1.96",
    "FirstIonizationPotential": "7.3439",
    "Density": "7.287",
    "MeltingPoint": "505.21",
    "BoilingPoint": "2875",
    "Isotopes": "28",
    "SpecificHeatCapacity": "0.228",
    "ElectronConfiguration": "[Kr] 4d10 5s2 5p2",
    "DisplayRow": "5",
    "DisplayColumn": "14",
    "Id": 50,
    "Guid": "f172d5b0-c333-44c0-a0d2-fe337525361e",
    "TimeAdded": "2023-09-21T04:51:35.567782+00:00",
    "UserAddedId": 1,
    "TimeModified": "2023-09-21T04:51:35.567782+00:00",
    "UserModifiedId": 1,
    "IsActive": true
  },
  {
    "AtomicNumber": "51",
    "ElementName": "Antimony",
    "Symbol": "Sb",
    "AtomicWeight": "121.76",
    "Period": "5",
    "Group": "15",
    "IonicRadius": "0.76",
    "AtomicRadius": "1.5",
    "Electronegativity": "2.05",
    "FirstIonizationPotential": "8.6084",
    "Density": "6.685",
    "MeltingPoint": "904.05",
    "BoilingPoint": "1860",
    "Isotopes": "29",
    "SpecificHeatCapacity": "0.207",
    "ElectronConfiguration": "[Kr] 4d10 5s2 5p3",
    "DisplayRow": "5",
    "DisplayColumn": "15",
    "Id": 51,
    "Guid": "aa652f93-b45a-45fc-9802-4651709f99f5",
    "TimeAdded": "2023-09-21T04:51:35.567782+00:00",
    "UserAddedId": 1,
    "TimeModified": "2023-09-21T04:51:35.567782+00:00",
    "UserModifiedId": 1,
    "IsActive": true
  },
  {
    "AtomicNumber": "52",
    "ElementName": "Tellurium",
    "Symbol": "Te",
    "AtomicWeight": "127.6",
    "Period": "5",
    "Group": "16",
    "IonicRadius": "0.97",
    "AtomicRadius": "1.4",
    "Electronegativity": "2.1",
    "FirstIonizationPotential": "9.0096",
    "Density": "6.232",
    "MeltingPoint": "722.8",
    "BoilingPoint": "1261",
    "Isotopes": "29",
    "SpecificHeatCapacity": "0.202",
    "ElectronConfiguration": "[Kr] 4d10 5s2 5p4",
    "DisplayRow": "5",
    "DisplayColumn": "16",
    "Id": 52,
    "Guid": "7a668a8f-44a7-4ab9-a253-9875ff70a434",
    "TimeAdded": "2023-09-21T04:51:35.567782+00:00",
    "UserAddedId": 1,
    "TimeModified": "2023-09-21T04:51:35.567782+00:00",
    "UserModifiedId": 1,
    "IsActive": true
  },
  {
    "AtomicNumber": "53",
    "ElementName": "Iodine",
    "Symbol": "I",
    "AtomicWeight": "126.90447",
    "Period": "5",
    "Group": "17",
    "IonicRadius": "2.2",
    "AtomicRadius": "1.3",
    "Electronegativity": "2.66",
    "FirstIonizationPotential": "10.4513",
    "Density": "4.93",
    "MeltingPoint": "386.65",
    "BoilingPoint": "457.4",
    "Isotopes": "24",
    "SpecificHeatCapacity": "0.214",
    "ElectronConfiguration": "[Kr] 4d10 5s2 5p5",
    "DisplayRow": "5",
    "DisplayColumn": "17",
    "Id": 53,
    "Guid": "3109a713-478e-4005-9d03-74f779473c69",
    "TimeAdded": "2023-09-21T04:51:35.567782+00:00",
    "UserAddedId": 1,
    "TimeModified": "2023-09-21T04:51:35.567782+00:00",
    "UserModifiedId": 1,
    "IsActive": true
  },
  {
    "AtomicNumber": "54",
    "ElementName": "Xenon",
    "Symbol": "Xe",
    "AtomicWeight": "131.293",
    "Period": "5",
    "Group": "18",
    "IonicRadius": "",
    "AtomicRadius": "1.2",
    "Electronegativity": "",
    "FirstIonizationPotential": "12.1298",
    "Density": "0.005887",
    "MeltingPoint": "161.45",
    "BoilingPoint": "165.03",
    "Isotopes": "31",
    "SpecificHeatCapacity": "0.158",
    "ElectronConfiguration": "[Kr] 4d10 5s2 5p6",
    "DisplayRow": "5",
    "DisplayColumn": "18",
    "Id": 54,
    "Guid": "791d363f-e3a7-492f-8bf4-a2637d4e10c1",
    "TimeAdded": "2023-09-21T04:51:35.567782+00:00",
    "UserAddedId": 1,
    "TimeModified": "2023-09-21T04:51:35.567782+00:00",
    "UserModifiedId": 1,
    "IsActive": true
  },
  {
    "AtomicNumber": "55",
    "ElementName": "Cesium",
    "Symbol": "Cs",
    "AtomicWeight": "132.9054519",
    "Period": "6",
    "Group": "1",
    "IonicRadius": "1.7",
    "AtomicRadius": "3.3",
    "Electronegativity": "0.79",
    "FirstIonizationPotential": "3.8939",
    "Density": "1.873",
    "MeltingPoint": "301.7",
    "BoilingPoint": "944",
    "Isotopes": "22",
    "SpecificHeatCapacity": "0.242",
    "ElectronConfiguration": "[Xe] 6s1",
    "DisplayRow": "6",
    "DisplayColumn": "1",
    "Id": 55,
    "Guid": "5f548beb-d531-43f4-b30d-11bd70d093de",
    "TimeAdded": "2023-09-21T04:51:35.567782+00:00",
    "UserAddedId": 1,
    "TimeModified": "2023-09-21T04:51:35.567782+00:00",
    "UserModifiedId": 1,
    "IsActive": true
  },
  {
    "AtomicNumber": "56",
    "ElementName": "Barium",
    "Symbol": "Ba",
    "AtomicWeight": "137.327",
    "Period": "6",
    "Group": "2",
    "IonicRadius": "1.4",
    "AtomicRadius": "2.8",
    "Electronegativity": "0.89",
    "FirstIonizationPotential": "5.2117",
    "Density": "3.594",
    "MeltingPoint": "1002.15",
    "BoilingPoint": "2170",
    "Isotopes": "25",
    "SpecificHeatCapacity": "0.204",
    "ElectronConfiguration": "[Xe] 6s2",
    "DisplayRow": "6",
    "DisplayColumn": "2",
    "Id": 56,
    "Guid": "f114eaea-b26b-47a1-ae25-a91705e11f44",
    "TimeAdded": "2023-09-21T04:51:35.567782+00:00",
    "UserAddedId": 1,
    "TimeModified": "2023-09-21T04:51:35.567782+00:00",
    "UserModifiedId": 1,
    "IsActive": true
  },
  {
    "AtomicNumber": "57",
    "ElementName": "Lanthanum",
    "Symbol": "La",
    "AtomicWeight": "138.90547",
    "Period": "6",
    "Group": "3",
    "IonicRadius": "1.1",
    "AtomicRadius": "2.7",
    "Electronegativity": "1.1",
    "FirstIonizationPotential": "5.5769",
    "Density": "6.145",
    "MeltingPoint": "1193.15",
    "BoilingPoint": "3737",
    "Isotopes": "19",
    "SpecificHeatCapacity": "0.195",
    "ElectronConfiguration": "[Xe] 5d1 6s2",
    "DisplayRow": "8",
    "DisplayColumn": "3",
    "Id": 57,
    "Guid": "358942b4-01be-4146-ae57-7c6e985ef738",
    "TimeAdded": "2023-09-21T04:51:35.567782+00:00",
    "UserAddedId": 1,
    "TimeModified": "2023-09-21T04:51:35.567782+00:00",
    "UserModifiedId": 1,
    "IsActive": true
  },
  {
    "AtomicNumber": "58",
    "ElementName": "Cerium",
    "Symbol": "Ce",
    "AtomicWeight": "140.116",
    "Period": "6",
    "Group": "19",
    "IonicRadius": "1",
    "AtomicRadius": "2.7",
    "Electronegativity": "1.12",
    "FirstIonizationPotential": "5.5387",
    "Density": "6.77",
    "MeltingPoint": "1071.15",
    "BoilingPoint": "3716",
    "Isotopes": "19",
    "SpecificHeatCapacity": "0.192",
    "ElectronConfiguration": "[Xe] 4f1 5d1 6s2",
    "DisplayRow": "8",
    "DisplayColumn": "4",
    "Id": 58,
    "Guid": "516ee167-52e1-464f-8e00-34635aa12359",
    "TimeAdded": "2023-09-21T04:51:35.567782+00:00",
    "UserAddedId": 1,
    "TimeModified": "2023-09-21T04:51:35.567782+00:00",
    "UserModifiedId": 1,
    "IsActive": true
  },
  {
    "AtomicNumber": "59",
    "ElementName": "Praseodymium",
    "Symbol": "Pr",
    "AtomicWeight": "140.90765",
    "Period": "6",
    "Group": "20",
    "IonicRadius": "1",
    "AtomicRadius": "2.7",
    "Electronegativity": "1.13",
    "FirstIonizationPotential": "5.473",
    "Density": "6.773",
    "MeltingPoint": "1204.15",
    "BoilingPoint": "3793",
    "Isotopes": "15",
    "SpecificHeatCapacity": "0.193",
    "ElectronConfiguration": "[Xe] 4f3 6s2",
    "DisplayRow": "8",
    "DisplayColumn": "5",
    "Id": 59,
    "Guid": "b668ff0a-46e6-46e0-bb7d-e3972ec503e4",
    "TimeAdded": "2023-09-21T04:51:35.567782+00:00",
    "UserAddedId": 1,
    "TimeModified": "2023-09-21T04:51:35.567782+00:00",
    "UserModifiedId": 1,
    "IsActive": true
  },
  {
    "AtomicNumber": "60",
    "ElementName": "Neodymium",
    "Symbol": "Nd",
    "AtomicWeight": "144.242",
    "Period": "6",
    "Group": "21",
    "IonicRadius": "1",
    "AtomicRadius": "2.6",
    "Electronegativity": "1.14",
    "FirstIonizationPotential": "5.525",
    "Density": "7.007",
    "MeltingPoint": "1289.15",
    "BoilingPoint": "3347",
    "Isotopes": "16",
    "SpecificHeatCapacity": "0.19",
    "ElectronConfiguration": "[Xe] 4f4 6s2",
    "DisplayRow": "8",
    "DisplayColumn": "6",
    "Id": 60,
    "Guid": "aad752c4-510c-4341-82b2-44a6c5736c1c",
    "TimeAdded": "2023-09-21T04:51:35.567782+00:00",
    "UserAddedId": 1,
    "TimeModified": "2023-09-21T04:51:35.567782+00:00",
    "UserModifiedId": 1,
    "IsActive": true
  },
  {
    "AtomicNumber": "61",
    "ElementName": "Promethium",
    "Symbol": "Pm",
    "AtomicWeight": "145",
    "Period": "6",
    "Group": "22",
    "IonicRadius": "0.98",
    "AtomicRadius": "2.6",
    "Electronegativity": "1.13",
    "FirstIonizationPotential": "5.582",
    "Density": "7.26",
    "MeltingPoint": "1204.15",
    "BoilingPoint": "3273",
    "Isotopes": "14",
    "SpecificHeatCapacity": "",
    "ElectronConfiguration": "[Xe] 4f5 6s2",
    "DisplayRow": "8",
    "DisplayColumn": "7",
    "Id": 61,
    "Guid": "8857aa47-10ca-4098-8309-ae2620c2f612",
    "TimeAdded": "2023-09-21T04:51:35.567782+00:00",
    "UserAddedId": 1,
    "TimeModified": "2023-09-21T04:51:35.567782+00:00",
    "UserModifiedId": 1,
    "IsActive": true
  },
  {
    "AtomicNumber": "62",
    "ElementName": "Samarium",
    "Symbol": "Sm",
    "AtomicWeight": "150.36",
    "Period": "6",
    "Group": "23",
    "IonicRadius": "0.96",
    "AtomicRadius": "2.6",
    "Electronegativity": "1.17",
    "FirstIonizationPotential": "5.6437",
    "Density": "7.52",
    "MeltingPoint": "1345.15",
    "BoilingPoint": "2067",
    "Isotopes": "17",
    "SpecificHeatCapacity": "0.197",
    "ElectronConfiguration": "[Xe] 4f6 6s2",
    "DisplayRow": "8",
    "DisplayColumn": "8",
    "Id": 62,
    "Guid": "cc63809d-c358-4e9d-a342-bf4b49d4b5e9",
    "TimeAdded": "2023-09-21T04:51:35.567782+00:00",
    "UserAddedId": 1,
    "TimeModified": "2023-09-21T04:51:35.567782+00:00",
    "UserModifiedId": 1,
    "IsActive": true
  },
  {
    "AtomicNumber": "63",
    "ElementName": "Europium",
    "Symbol": "Eu",
    "AtomicWeight": "151.964",
    "Period": "6",
    "Group": "24",
    "IonicRadius": "0.95",
    "AtomicRadius": "2.6",
    "Electronegativity": "1.2",
    "FirstIonizationPotential": "5.6704",
    "Density": "5.243",
    "MeltingPoint": "1095.15",
    "BoilingPoint": "1802",
    "Isotopes": "21",
    "SpecificHeatCapacity": "0.182",
    "ElectronConfiguration": "[Xe] 4f7 6s2",
    "DisplayRow": "8",
    "DisplayColumn": "9",
    "Id": 63,
    "Guid": "17b4906d-b165-4aaa-b7cc-50eb22bb831f",
    "TimeAdded": "2023-09-21T04:51:35.567782+00:00",
    "UserAddedId": 1,
    "TimeModified": "2023-09-21T04:51:35.567782+00:00",
    "UserModifiedId": 1,
    "IsActive": true
  },
  {
    "AtomicNumber": "64",
    "ElementName": "Gadolinium",
    "Symbol": "Gd",
    "AtomicWeight": "157.25",
    "Period": "6",
    "Group": "25",
    "IonicRadius": "0.94",
    "AtomicRadius": "2.5",
    "Electronegativity": "1.2",
    "FirstIonizationPotential": "6.1501",
    "Density": "7.895",
    "MeltingPoint": "1585.15",
    "BoilingPoint": "3546",
    "Isotopes": "17",
    "SpecificHeatCapacity": "0.236",
    "ElectronConfiguration": "[Xe] 4f7 5d1 6s2",
    "DisplayRow": "8",
    "DisplayColumn": "10",
    "Id": 64,
    "Guid": "da5b7dfd-5c3a-4938-a836-a383bc1fab60",
    "TimeAdded": "2023-09-21T04:51:35.567782+00:00",
    "UserAddedId": 1,
    "TimeModified": "2023-09-21T04:51:35.567782+00:00",
    "UserModifiedId": 1,
    "IsActive": true
  },
  {
    "AtomicNumber": "65",
    "ElementName": "Terbium",
    "Symbol": "Tb",
    "AtomicWeight": "158.92535",
    "Period": "6",
    "Group": "26",
    "IonicRadius": "0.92",
    "AtomicRadius": "2.5",
    "Electronegativity": "1.2",
    "FirstIonizationPotential": "5.8638",
    "Density": "8.229",
    "MeltingPoint": "1630.15",
    "BoilingPoint": "3503",
    "Isotopes": "24",
    "SpecificHeatCapacity": "0.182",
    "ElectronConfiguration": "[Xe] 4f9 6s2",
    "DisplayRow": "8",
    "DisplayColumn": "11",
    "Id": 65,
    "Guid": "c8d0274d-c9f9-49d6-a59c-20731d92c3b7",
    "TimeAdded": "2023-09-21T04:51:35.567782+00:00",
    "UserAddedId": 1,
    "TimeModified": "2023-09-21T04:51:35.567782+00:00",
    "UserModifiedId": 1,
    "IsActive": true
  },
  {
    "AtomicNumber": "66",
    "ElementName": "Dysprosium",
    "Symbol": "Dy",
    "AtomicWeight": "162.5",
    "Period": "6",
    "Group": "27",
    "IonicRadius": "0.91",
    "AtomicRadius": "2.5",
    "Electronegativity": "1.22",
    "FirstIonizationPotential": "5.9389",
    "Density": "8.55",
    "MeltingPoint": "1680.15",
    "BoilingPoint": "2840",
    "Isotopes": "21",
    "SpecificHeatCapacity": "0.17",
    "ElectronConfiguration": "[Xe] 4f10 6s2",
    "DisplayRow": "8",
    "DisplayColumn": "12",
    "Id": 66,
    "Guid": "dbdd5c5f-de92-4705-b5b7-73ed9b75192f",
    "TimeAdded": "2023-09-21T04:51:35.567782+00:00",
    "UserAddedId": 1,
    "TimeModified": "2023-09-21T04:51:35.567782+00:00",
    "UserModifiedId": 1,
    "IsActive": true
  },
  {
    "AtomicNumber": "67",
    "ElementName": "Holmium",
    "Symbol": "Ho",
    "AtomicWeight": "164.93032",
    "Period": "6",
    "Group": "28",
    "IonicRadius": "0.9",
    "AtomicRadius": "2.5",
    "Electronegativity": "1.23",
    "FirstIonizationPotential": "6.0215",
    "Density": "8.795",
    "MeltingPoint": "1743.15",
    "BoilingPoint": "2993",
    "Isotopes": "29",
    "SpecificHeatCapacity": "0.165",
    "ElectronConfiguration": "[Xe] 4f11 6s2",
    "DisplayRow": "8",
    "DisplayColumn": "13",
    "Id": 67,
    "Guid": "5ca50ae8-08f2-40c5-8615-4ac518f10026",
    "TimeAdded": "2023-09-21T04:51:35.567782+00:00",
    "UserAddedId": 1,
    "TimeModified": "2023-09-21T04:51:35.567782+00:00",
    "UserModifiedId": 1,
    "IsActive": true
  },
  {
    "AtomicNumber": "68",
    "ElementName": "Erbium",
    "Symbol": "Er",
    "AtomicWeight": "167.259",
    "Period": "6",
    "Group": "29",
    "IonicRadius": "0.88",
    "AtomicRadius": "2.5",
    "Electronegativity": "1.24",
    "FirstIonizationPotential": "6.1077",
    "Density": "9.066",
    "MeltingPoint": "1795.15",
    "BoilingPoint": "3503",
    "Isotopes": "16",
    "SpecificHeatCapacity": "0.168",
    "ElectronConfiguration": "[Xe] 4f12 6s2",
    "DisplayRow": "8",
    "DisplayColumn": "14",
    "Id": 68,
    "Guid": "280f74c0-aee4-4041-9ccf-543acbc58c4b",
    "TimeAdded": "2023-09-21T04:51:35.567782+00:00",
    "UserAddedId": 1,
    "TimeModified": "2023-09-21T04:51:35.567782+00:00",
    "UserModifiedId": 1,
    "IsActive": true
  },
  {
    "AtomicNumber": "69",
    "ElementName": "Thulium",
    "Symbol": "Tm",
    "AtomicWeight": "168.93421",
    "Period": "6",
    "Group": "30",
    "IonicRadius": "0.87",
    "AtomicRadius": "2.4",
    "Electronegativity": "1.25",
    "FirstIonizationPotential": "6.1843",
    "Density": "9.321",
    "MeltingPoint": "1818.15",
    "BoilingPoint": "2223",
    "Isotopes": "18",
    "SpecificHeatCapacity": "0.16",
    "ElectronConfiguration": "[Xe] 4f13 6s2",
    "DisplayRow": "8",
    "DisplayColumn": "15",
    "Id": 69,
    "Guid": "46a4042c-ab29-4138-8823-0e1af9d45efc",
    "TimeAdded": "2023-09-21T04:51:35.567782+00:00",
    "UserAddedId": 1,
    "TimeModified": "2023-09-21T04:51:35.567782+00:00",
    "UserModifiedId": 1,
    "IsActive": true
  },
  {
    "AtomicNumber": "70",
    "ElementName": "Ytterbium",
    "Symbol": "Yb",
    "AtomicWeight": "173.054",
    "Period": "6",
    "Group": "31",
    "IonicRadius": "0.86",
    "AtomicRadius": "2.4",
    "Electronegativity": "1.1",
    "FirstIonizationPotential": "6.2542",
    "Density": "6.965",
    "MeltingPoint": "1097.15",
    "BoilingPoint": "1469",
    "Isotopes": "16",
    "SpecificHeatCapacity": "0.155",
    "ElectronConfiguration": "[Xe] 4f14 6s2",
    "DisplayRow": "8",
    "DisplayColumn": "16",
    "Id": 70,
    "Guid": "b39d069a-bf94-4de5-a1ca-ba75359a9d51",
    "TimeAdded": "2023-09-21T04:51:35.567782+00:00",
    "UserAddedId": 1,
    "TimeModified": "2023-09-21T04:51:35.567782+00:00",
    "UserModifiedId": 1,
    "IsActive": true
  },
  {
    "AtomicNumber": "71",
    "ElementName": "Lutetium",
    "Symbol": "Lu",
    "AtomicWeight": "174.9668",
    "Period": "6",
    "Group": "32",
    "IonicRadius": "0.85",
    "AtomicRadius": "2.3",
    "Electronegativity": "1.27",
    "FirstIonizationPotential": "5.4259",
    "Density": "9.84",
    "MeltingPoint": "1936.15",
    "BoilingPoint": "3675",
    "Isotopes": "22",
    "SpecificHeatCapacity": "0.154",
    "ElectronConfiguration": "[Xe] 4f14 5d1 6s2",
    "DisplayRow": "8",
    "DisplayColumn": "17",
    "Id": 71,
    "Guid": "19481025-cdc9-427e-8a83-921528abdf19",
    "TimeAdded": "2023-09-21T04:51:35.567782+00:00",
    "UserAddedId": 1,
    "TimeModified": "2023-09-21T04:51:35.567782+00:00",
    "UserModifiedId": 1,
    "IsActive": true
  },
  {
    "AtomicNumber": "72",
    "ElementName": "Hafnium",
    "Symbol": "Hf",
    "AtomicWeight": "178.49",
    "Period": "6",
    "Group": "4",
    "IonicRadius": "0.71",
    "AtomicRadius": "2.2",
    "Electronegativity": "1.3",
    "FirstIonizationPotential": "6.8251",
    "Density": "13.31",
    "MeltingPoint": "2500.15",
    "BoilingPoint": "4876",
    "Isotopes": "17",
    "SpecificHeatCapacity": "0.144",
    "ElectronConfiguration": "[Xe] 4f14 5d2 6s2",
    "DisplayRow": "6",
    "DisplayColumn": "4",
    "Id": 72,
    "Guid": "23320800-3078-4050-9b84-83b025a114c5",
    "TimeAdded": "2023-09-21T04:51:35.567782+00:00",
    "UserAddedId": 1,
    "TimeModified": "2023-09-21T04:51:35.567782+00:00",
    "UserModifiedId": 1,
    "IsActive": true
  },
  {
    "AtomicNumber": "73",
    "ElementName": "Tantalum",
    "Symbol": "Ta",
    "AtomicWeight": "180.94788",
    "Period": "6",
    "Group": "5",
    "IonicRadius": "0.64",
    "AtomicRadius": "2.1",
    "Electronegativity": "1.5",
    "FirstIonizationPotential": "7.5496",
    "Density": "16.654",
    "MeltingPoint": "3269.15",
    "BoilingPoint": "5731",
    "Isotopes": "19",
    "SpecificHeatCapacity": "0.14",
    "ElectronConfiguration": "[Xe] 4f14 5d3 6s2",
    "DisplayRow": "6",
    "DisplayColumn": "5",
    "Id": 73,
    "Guid": "9e965f9b-2b91-4b27-9a73-4b1a5da7f872",
    "TimeAdded": "2023-09-21T04:51:35.567782+00:00",
    "UserAddedId": 1,
    "TimeModified": "2023-09-21T04:51:35.567782+00:00",
    "UserModifiedId": 1,
    "IsActive": true
  },
  {
    "AtomicNumber": "74",
    "ElementName": "Wolfram",
    "Symbol": "W",
    "AtomicWeight": "183.84",
    "Period": "6",
    "Group": "6",
    "IonicRadius": "0.62",
    "AtomicRadius": "2",
    "Electronegativity": "2.36",
    "FirstIonizationPotential": "7.864",
    "Density": "19.25",
    "MeltingPoint": "3680.15",
    "BoilingPoint": "5828",
    "Isotopes": "22",
    "SpecificHeatCapacity": "0.132",
    "ElectronConfiguration": "[Xe] 4f14 5d4 6s2",
    "DisplayRow": "6",
    "DisplayColumn": "6",
    "Id": 74,
    "Guid": "1100ca21-26cf-4d45-bd4c-a356defd31ac",
    "TimeAdded": "2023-09-21T04:51:35.567782+00:00",
    "UserAddedId": 1,
    "TimeModified": "2023-09-21T04:51:35.567782+00:00",
    "UserModifiedId": 1,
    "IsActive": true
  },
  {
    "AtomicNumber": "75",
    "ElementName": "Rhenium",
    "Symbol": "Re",
    "AtomicWeight": "186.207",
    "Period": "6",
    "Group": "7",
    "IonicRadius": "0.56",
    "AtomicRadius": "2",
    "Electronegativity": "1.9",
    "FirstIonizationPotential": "7.8335",
    "Density": "21.02",
    "MeltingPoint": "3453.15",
    "BoilingPoint": "5869",
    "Isotopes": "21",
    "SpecificHeatCapacity": "0.137",
    "ElectronConfiguration": "[Xe] 4f14 5d5 6s2",
    "DisplayRow": "6",
    "DisplayColumn": "7",
    "Id": 75,
    "Guid": "5b0527ac-96d4-4f94-a436-773ce9b15aeb",
    "TimeAdded": "2023-09-21T04:51:35.567782+00:00",
    "UserAddedId": 1,
    "TimeModified": "2023-09-21T04:51:35.567782+00:00",
    "UserModifiedId": 1,
    "IsActive": true
  },
  {
    "AtomicNumber": "76",
    "ElementName": "Osmium",
    "Symbol": "Os",
    "AtomicWeight": "190.23",
    "Period": "6",
    "Group": "8",
    "IonicRadius": "0.63",
    "AtomicRadius": "1.9",
    "Electronegativity": "2.2",
    "FirstIonizationPotential": "8.4382",
    "Density": "22.61",
    "MeltingPoint": "3300.15",
    "BoilingPoint": "5285",
    "Isotopes": "19",
    "SpecificHeatCapacity": "0.13",
    "ElectronConfiguration": "[Xe] 4f14 5d6 6s2",
    "DisplayRow": "6",
    "DisplayColumn": "8",
    "Id": 76,
    "Guid": "7648d00f-68dc-4a10-b543-6a45c4b5c38a",
    "TimeAdded": "2023-09-21T04:51:35.567782+00:00",
    "UserAddedId": 1,
    "TimeModified": "2023-09-21T04:51:35.567782+00:00",
    "UserModifiedId": 1,
    "IsActive": true
  },
  {
    "AtomicNumber": "77",
    "ElementName": "Iridium",
    "Symbol": "Ir",
    "AtomicWeight": "192.217",
    "Period": "6",
    "Group": "9",
    "IonicRadius": "0.63",
    "AtomicRadius": "1.9",
    "Electronegativity": "2.2",
    "FirstIonizationPotential": "8.967",
    "Density": "22.56",
    "MeltingPoint": "2716.15",
    "BoilingPoint": "4701",
    "Isotopes": "25",
    "SpecificHeatCapacity": "0.131",
    "ElectronConfiguration": "[Xe] 4f14 5d7 6s2",
    "DisplayRow": "6",
    "DisplayColumn": "9",
    "Id": 77,
    "Guid": "476fc6fc-881f-4c03-a955-33b89056f5fb",
    "TimeAdded": "2023-09-21T04:51:35.567782+00:00",
    "UserAddedId": 1,
    "TimeModified": "2023-09-21T04:51:35.567782+00:00",
    "UserModifiedId": 1,
    "IsActive": true
  },
  {
    "AtomicNumber": "78",
    "ElementName": "Platinum",
    "Symbol": "Pt",
    "AtomicWeight": "195.084",
    "Period": "6",
    "Group": "10",
    "IonicRadius": "0.63",
    "AtomicRadius": "1.8",
    "Electronegativity": "2.28",
    "FirstIonizationPotential": "8.9587",
    "Density": "21.46",
    "MeltingPoint": "2045.15",
    "BoilingPoint": "4098",
    "Isotopes": "32",
    "SpecificHeatCapacity": "0.133",
    "ElectronConfiguration": "[Xe] 4f14 5d9 6s1",
    "DisplayRow": "6",
    "DisplayColumn": "10",
    "Id": 78,
    "Guid": "25308ed5-1a14-46c0-bf0d-0b387c0a3f29",
    "TimeAdded": "2023-09-21T04:51:35.567782+00:00",
    "UserAddedId": 1,
    "TimeModified": "2023-09-21T04:51:35.567782+00:00",
    "UserModifiedId": 1,
    "IsActive": true
  },
  {
    "AtomicNumber": "79",
    "ElementName": "Gold",
    "Symbol": "Au",
    "AtomicWeight": "196.966569",
    "Period": "6",
    "Group": "11",
    "IonicRadius": "0.85",
    "AtomicRadius": "1.8",
    "Electronegativity": "2.54",
    "FirstIonizationPotential": "9.2255",
    "Density": "19.282",
    "MeltingPoint": "1337.73",
    "BoilingPoint": "3129",
    "Isotopes": "21",
    "SpecificHeatCapacity": "0.129",
    "ElectronConfiguration": "[Xe] 4f14 5d10 6s1",
    "DisplayRow": "6",
    "DisplayColumn": "11",
    "Id": 79,
    "Guid": "9c94d0c0-d00a-40a7-8e4c-a80ae4d3693d",
    "TimeAdded": "2023-09-21T04:51:35.567782+00:00",
    "UserAddedId": 1,
    "TimeModified": "2023-09-21T04:51:35.567782+00:00",
    "UserModifiedId": 1,
    "IsActive": true
  },
  {
    "AtomicNumber": "80",
    "ElementName": "Mercury",
    "Symbol": "Hg",
    "AtomicWeight": "200.59",
    "Period": "6",
    "Group": "12",
    "IonicRadius": "1",
    "AtomicRadius": "1.8",
    "Electronegativity": "2",
    "FirstIonizationPotential": "10.4375",
    "Density": "13.5336",
    "MeltingPoint": "234.43",
    "BoilingPoint": "630",
    "Isotopes": "26",
    "SpecificHeatCapacity": "0.14",
    "ElectronConfiguration": "[Xe] 4f14 5d10 6s2",
    "DisplayRow": "6",
    "DisplayColumn": "12",
    "Id": 80,
    "Guid": "ee770938-8950-4c58-be5f-2561a49e7f68",
    "TimeAdded": "2023-09-21T04:51:35.567782+00:00",
    "UserAddedId": 1,
    "TimeModified": "2023-09-21T04:51:35.567782+00:00",
    "UserModifiedId": 1,
    "IsActive": true
  },
  {
    "AtomicNumber": "81",
    "ElementName": "Thallium",
    "Symbol": "Tl",
    "AtomicWeight": "204.3833",
    "Period": "6",
    "Group": "13",
    "IonicRadius": "1.5",
    "AtomicRadius": "2.1",
    "Electronegativity": "2.04",
    "FirstIonizationPotential": "6.1082",
    "Density": "11.85",
    "MeltingPoint": "577.15",
    "BoilingPoint": "1746",
    "Isotopes": "28",
    "SpecificHeatCapacity": "0.129",
    "ElectronConfiguration": "[Xe] 4f14 5d10 6s2 6p1",
    "DisplayRow": "6",
    "DisplayColumn": "13",
    "Id": 81,
    "Guid": "a2ced02c-2ddb-4e73-b152-03126cffb987",
    "TimeAdded": "2023-09-21T04:51:35.567782+00:00",
    "UserAddedId": 1,
    "TimeModified": "2023-09-21T04:51:35.567782+00:00",
    "UserModifiedId": 1,
    "IsActive": true
  },
  {
    "AtomicNumber": "82",
    "ElementName": "Lead",
    "Symbol": "Pb",
    "AtomicWeight": "207.2",
    "Period": "6",
    "Group": "14",
    "IonicRadius": "1.2",
    "AtomicRadius": "1.8",
    "Electronegativity": "2.33",
    "FirstIonizationPotential": "7.4167",
    "Density": "11.342",
    "MeltingPoint": "600.75",
    "BoilingPoint": "2022",
    "Isotopes": "29",
    "SpecificHeatCapacity": "0.129",
    "ElectronConfiguration": "[Xe] 4f14 5d10 6s2 6p2",
    "DisplayRow": "6",
    "DisplayColumn": "14",
    "Id": 82,
    "Guid": "a9376b7c-96f4-4ae4-bffd-a39217ef37b3",
    "TimeAdded": "2023-09-21T04:51:35.567782+00:00",
    "UserAddedId": 1,
    "TimeModified": "2023-09-21T04:51:35.567782+00:00",
    "UserModifiedId": 1,
    "IsActive": true
  },
  {
    "AtomicNumber": "83",
    "ElementName": "Bismuth",
    "Symbol": "Bi",
    "AtomicWeight": "208.9804",
    "Period": "6",
    "Group": "15",
    "IonicRadius": "1",
    "AtomicRadius": "1.6",
    "Electronegativity": "2.02",
    "FirstIonizationPotential": "7.2856",
    "Density": "9.807",
    "MeltingPoint": "544.67",
    "BoilingPoint": "1837",
    "Isotopes": "19",
    "SpecificHeatCapacity": "0.122",
    "ElectronConfiguration": "[Xe] 4f14 5d10 6s2 6p3",
    "DisplayRow": "6",
    "DisplayColumn": "15",
    "Id": 83,
    "Guid": "ed8c8852-77c0-4678-a9e9-8702a9ecf070",
    "TimeAdded": "2023-09-21T04:51:35.567782+00:00",
    "UserAddedId": 1,
    "TimeModified": "2023-09-21T04:51:35.567782+00:00",
    "UserModifiedId": 1,
    "IsActive": true
  },
  {
    "AtomicNumber": "84",
    "ElementName": "Polonium",
    "Symbol": "Po",
    "AtomicWeight": "210",
    "Period": "6",
    "Group": "16",
    "IonicRadius": "2.3",
    "AtomicRadius": "1.5",
    "Electronegativity": "2",
    "FirstIonizationPotential": "8.417",
    "Density": "9.32",
    "MeltingPoint": "527.15",
    "BoilingPoint": "1235",
    "Isotopes": "34",
    "SpecificHeatCapacity": "",
    "ElectronConfiguration": "[Xe] 4f14 5d10 6s2 6p4",
    "DisplayRow": "6",
    "DisplayColumn": "16",
    "Id": 84,
    "Guid": "ded5ade1-9e6e-4fec-97a5-8cfbb80c092f",
    "TimeAdded": "2023-09-21T04:51:35.567782+00:00",
    "UserAddedId": 1,
    "TimeModified": "2023-09-21T04:51:35.567782+00:00",
    "UserModifiedId": 1,
    "IsActive": true
  },
  {
    "AtomicNumber": "85",
    "ElementName": "Astatine",
    "Symbol": "At",
    "AtomicWeight": "210",
    "Period": "6",
    "Group": "17",
    "IonicRadius": "",
    "AtomicRadius": "1.4",
    "Electronegativity": "2.2",
    "FirstIonizationPotential": "9.3",
    "Density": "7",
    "MeltingPoint": "575.15",
    "BoilingPoint": "610",
    "Isotopes": "21",
    "SpecificHeatCapacity": "",
    "ElectronConfiguration": "[Xe] 4f14 5d10 6s2 6p5",
    "DisplayRow": "6",
    "DisplayColumn": "17",
    "Id": 85,
    "Guid": "fd2535a7-1cee-4a22-a65f-6531add08d2d",
    "TimeAdded": "2023-09-21T04:51:35.567782+00:00",
    "UserAddedId": 1,
    "TimeModified": "2023-09-21T04:51:35.567782+00:00",
    "UserModifiedId": 1,
    "IsActive": true
  },
  {
    "AtomicNumber": "86",
    "ElementName": "Radon",
    "Symbol": "Rn",
    "AtomicWeight": "222",
    "Period": "6",
    "Group": "18",
    "IonicRadius": "",
    "AtomicRadius": "1.3",
    "Electronegativity": "",
    "FirstIonizationPotential": "10.7485",
    "Density": "0.00973",
    "MeltingPoint": "202.15",
    "BoilingPoint": "211.3",
    "Isotopes": "20",
    "SpecificHeatCapacity": "0.094",
    "ElectronConfiguration": "[Xe] 4f14 5d10 6s2 6p6",
    "DisplayRow": "6",
    "DisplayColumn": "18",
    "Id": 86,
    "Guid": "397f50cc-e295-4cee-95b3-65d81f31c1df",
    "TimeAdded": "2023-09-21T04:51:35.567782+00:00",
    "UserAddedId": 1,
    "TimeModified": "2023-09-21T04:51:35.567782+00:00",
    "UserModifiedId": 1,
    "IsActive": true
  },
  {
    "AtomicNumber": "87",
    "ElementName": "Francium",
    "Symbol": "Fr",
    "AtomicWeight": "223",
    "Period": "7",
    "Group": "1",
    "IonicRadius": "1.8",
    "AtomicRadius": "",
    "Electronegativity": "0.7",
    "FirstIonizationPotential": "4.0727",
    "Density": "1.87",
    "MeltingPoint": "300.15",
    "BoilingPoint": "950",
    "Isotopes": "21",
    "SpecificHeatCapacity": "",
    "ElectronConfiguration": "[Rn] 7s1",
    "DisplayRow": "7",
    "DisplayColumn": "1",
    "Id": 87,
    "Guid": "e6a6541e-28f7-4a32-8b0d-0b6001863306",
    "TimeAdded": "2023-09-21T04:51:35.567782+00:00",
    "UserAddedId": 1,
    "TimeModified": "2023-09-21T04:51:35.567782+00:00",
    "UserModifiedId": 1,
    "IsActive": true
  },
  {
    "AtomicNumber": "88",
    "ElementName": "Radium",
    "Symbol": "Ra",
    "AtomicWeight": "226",
    "Period": "7",
    "Group": "2",
    "IonicRadius": "1.4",
    "AtomicRadius": "",
    "Electronegativity": "0.9",
    "FirstIonizationPotential": "5.2784",
    "Density": "5.5",
    "MeltingPoint": "973.15",
    "BoilingPoint": "2010",
    "Isotopes": "15",
    "SpecificHeatCapacity": "",
    "ElectronConfiguration": "[Rn] 7s2",
    "DisplayRow": "7",
    "DisplayColumn": "2",
    "Id": 88,
    "Guid": "6ff8a279-4968-42cf-b67d-457e8101b3da",
    "TimeAdded": "2023-09-21T04:51:35.567782+00:00",
    "UserAddedId": 1,
    "TimeModified": "2023-09-21T04:51:35.567782+00:00",
    "UserModifiedId": 1,
    "IsActive": true
  },
  {
    "AtomicNumber": "89",
    "ElementName": "Actinium",
    "Symbol": "Ac",
    "AtomicWeight": "227",
    "Period": "7",
    "Group": "3",
    "IonicRadius": "1.1",
    "AtomicRadius": "",
    "Electronegativity": "1.1",
    "FirstIonizationPotential": "5.17",
    "Density": "10.07",
    "MeltingPoint": "1323.15",
    "BoilingPoint": "3471",
    "Isotopes": "11",
    "SpecificHeatCapacity": "0.12",
    "ElectronConfiguration": "[Rn] 6d1 7s2",
    "DisplayRow": "9",
    "DisplayColumn": "3",
    "Id": 89,
    "Guid": "f05dba6d-3b90-4e12-a511-5c35745ea873",
    "TimeAdded": "2023-09-21T04:51:35.567782+00:00",
    "UserAddedId": 1,
    "TimeModified": "2023-09-21T04:51:35.567782+00:00",
    "UserModifiedId": 1,
    "IsActive": true
  },
  {
    "AtomicNumber": "90",
    "ElementName": "Thorium",
    "Symbol": "Th",
    "AtomicWeight": "232.03806",
    "Period": "7",
    "Group": "19",
    "IonicRadius": "0.97",
    "AtomicRadius": "",
    "Electronegativity": "1.3",
    "FirstIonizationPotential": "6.3067",
    "Density": "11.72",
    "MeltingPoint": "2028.15",
    "BoilingPoint": "5061",
    "Isotopes": "12",
    "SpecificHeatCapacity": "0.113",
    "ElectronConfiguration": "[Rn] 6d2 7s2",
    "DisplayRow": "9",
    "DisplayColumn": "4",
    "Id": 90,
    "Guid": "caba3b54-5e7d-4b6e-b5d9-9dc93b80e0ef",
    "TimeAdded": "2023-09-21T04:51:35.567782+00:00",
    "UserAddedId": 1,
    "TimeModified": "2023-09-21T04:51:35.567782+00:00",
    "UserModifiedId": 1,
    "IsActive": true
  },
  {
    "AtomicNumber": "91",
    "ElementName": "Protactinium",
    "Symbol": "Pa",
    "AtomicWeight": "231.03588",
    "Period": "7",
    "Group": "20",
    "IonicRadius": "0.78",
    "AtomicRadius": "",
    "Electronegativity": "1.5",
    "FirstIonizationPotential": "5.89",
    "Density": "15.37",
    "MeltingPoint": "1873.15",
    "BoilingPoint": "4300",
    "Isotopes": "14",
    "SpecificHeatCapacity": "",
    "ElectronConfiguration": "[Rn] 5f2 6d1 7s2",
    "DisplayRow": "9",
    "DisplayColumn": "5",
    "Id": 91,
    "Guid": "9926ac39-537e-4ae3-92ea-e416bd2cf617",
    "TimeAdded": "2023-09-21T04:51:35.567782+00:00",
    "UserAddedId": 1,
    "TimeModified": "2023-09-21T04:51:35.567782+00:00",
    "UserModifiedId": 1,
    "IsActive": true
  },
  {
    "AtomicNumber": "92",
    "ElementName": "Uranium",
    "Symbol": "U",
    "AtomicWeight": "238.02891",
    "Period": "7",
    "Group": "21",
    "IonicRadius": "0.52",
    "AtomicRadius": "",
    "Electronegativity": "1.38",
    "FirstIonizationPotential": "6.1941",
    "Density": "18.95",
    "MeltingPoint": "1405.15",
    "BoilingPoint": "4404",
    "Isotopes": "15",
    "SpecificHeatCapacity": "0.116",
    "ElectronConfiguration": "[Rn] 5f3 6d1 7s2",
    "DisplayRow": "9",
    "DisplayColumn": "6",
    "Id": 92,
    "Guid": "5ae5369b-f844-4eb5-813a-f5efb6b1bb2d",
    "TimeAdded": "2023-09-21T04:51:35.567782+00:00",
    "UserAddedId": 1,
    "TimeModified": "2023-09-21T04:51:35.567782+00:00",
    "UserModifiedId": 1,
    "IsActive": true
  },
  {
    "AtomicNumber": "93",
    "ElementName": "Neptunium",
    "Symbol": "Np",
    "AtomicWeight": "237",
    "Period": "7",
    "Group": "22",
    "IonicRadius": "0.75",
    "AtomicRadius": "",
    "Electronegativity": "1.36",
    "FirstIonizationPotential": "6.2657",
    "Density": "20.45",
    "MeltingPoint": "913.15",
    "BoilingPoint": "4273",
    "Isotopes": "153",
    "SpecificHeatCapacity": "",
    "ElectronConfiguration": "[Rn] 5f4 6d1 7s2",
    "DisplayRow": "9",
    "DisplayColumn": "7",
    "Id": 93,
    "Guid": "f9598d5c-8e86-40f9-9ea1-c00d82fb14af",
    "TimeAdded": "2023-09-21T04:51:35.567782+00:00",
    "UserAddedId": 1,
    "TimeModified": "2023-09-21T04:51:35.567782+00:00",
    "UserModifiedId": 1,
    "IsActive": true
  },
  {
    "AtomicNumber": "94",
    "ElementName": "Plutonium",
    "Symbol": "Pu",
    "AtomicWeight": "244",
    "Period": "7",
    "Group": "23",
    "IonicRadius": "0.89",
    "AtomicRadius": "",
    "Electronegativity": "1.28",
    "FirstIonizationPotential": "6.0262",
    "Density": "19.84",
    "MeltingPoint": "913.15",
    "BoilingPoint": "3501",
    "Isotopes": "163",
    "SpecificHeatCapacity": "",
    "ElectronConfiguration": "[Rn] 5f6 7s2",
    "DisplayRow": "9",
    "DisplayColumn": "8",
    "Id": 94,
    "Guid": "0378b555-21a1-44b0-80c5-580cff7a63ed",
    "TimeAdded": "2023-09-21T04:51:35.567782+00:00",
    "UserAddedId": 1,
    "TimeModified": "2023-09-21T04:51:35.567782+00:00",
    "UserModifiedId": 1,
    "IsActive": true
  },
  {
    "AtomicNumber": "95",
    "ElementName": "Americium",
    "Symbol": "Am",
    "AtomicWeight": "243",
    "Period": "7",
    "Group": "24",
    "IonicRadius": "0.98",
    "AtomicRadius": "",
    "Electronegativity": "1.3",
    "FirstIonizationPotential": "5.9738",
    "Density": "13.69",
    "MeltingPoint": "1267.15",
    "BoilingPoint": "2880",
    "Isotopes": "133",
    "SpecificHeatCapacity": "",
    "ElectronConfiguration": "[Rn] 5f7 7s2",
    "DisplayRow": "9",
    "DisplayColumn": "9",
    "Id": 95,
    "Guid": "60bd22ed-fad6-4840-bd3f-48023ccab687",
    "TimeAdded": "2023-09-21T04:51:35.567782+00:00",
    "UserAddedId": 1,
    "TimeModified": "2023-09-21T04:51:35.567782+00:00",
    "UserModifiedId": 1,
    "IsActive": true
  },
  {
    "AtomicNumber": "96",
    "ElementName": "Curium",
    "Symbol": "Cm",
    "AtomicWeight": "247",
    "Period": "7",
    "Group": "25",
    "IonicRadius": "0.97",
    "AtomicRadius": "",
    "Electronegativity": "1.3",
    "FirstIonizationPotential": "5.9915",
    "Density": "13.51",
    "MeltingPoint": "1340.15",
    "BoilingPoint": "3383",
    "Isotopes": "133",
    "SpecificHeatCapacity": "",
    "ElectronConfiguration": "",
    "DisplayRow": "9",
    "DisplayColumn": "10",
    "Id": 96,
    "Guid": "2e311298-5af2-4845-8d56-098e9dc13f8d",
    "TimeAdded": "2023-09-21T04:51:35.567782+00:00",
    "UserAddedId": 1,
    "TimeModified": "2023-09-21T04:51:35.567782+00:00",
    "UserModifiedId": 1,
    "IsActive": true
  },
  {
    "AtomicNumber": "97",
    "ElementName": "Berkelium",
    "Symbol": "Bk",
    "AtomicWeight": "247",
    "Period": "7",
    "Group": "26",
    "IonicRadius": "0.95",
    "AtomicRadius": "",
    "Electronegativity": "1.3",
    "FirstIonizationPotential": "6.1979",
    "Density": "14.79",
    "MeltingPoint": "1259.15",
    "BoilingPoint": "983",
    "Isotopes": "83",
    "SpecificHeatCapacity": "",
    "ElectronConfiguration": "",
    "DisplayRow": "9",
    "DisplayColumn": "11",
    "Id": 97,
    "Guid": "1d826c9c-870c-4cd1-bbc6-3492968d05d6",
    "TimeAdded": "2023-09-21T04:51:35.568782+00:00",
    "UserAddedId": 1,
    "TimeModified": "2023-09-21T04:51:35.568782+00:00",
    "UserModifiedId": 1,
    "IsActive": true
  },
  {
    "AtomicNumber": "98",
    "ElementName": "Californium",
    "Symbol": "Cf",
    "AtomicWeight": "251",
    "Period": "7",
    "Group": "27",
    "IonicRadius": "0.93",
    "AtomicRadius": "",
    "Electronegativity": "1.3",
    "FirstIonizationPotential": "6.2817",
    "Density": "15.1",
    "MeltingPoint": "1925.15",
    "BoilingPoint": "1173",
    "Isotopes": "123",
    "SpecificHeatCapacity": "",
    "ElectronConfiguration": "",
    "DisplayRow": "9",
    "DisplayColumn": "12",
    "Id": 98,
    "Guid": "c8454eba-1177-42dc-b60c-5b252df6e1c3",
    "TimeAdded": "2023-09-21T04:51:35.568782+00:00",
    "UserAddedId": 1,
    "TimeModified": "2023-09-21T04:51:35.568782+00:00",
    "UserModifiedId": 1,
    "IsActive": true
  },
  {
    "AtomicNumber": "99",
    "ElementName": "Einsteinium",
    "Symbol": "Es",
    "AtomicWeight": "252",
    "Period": "7",
    "Group": "28",
    "IonicRadius": "",
    "AtomicRadius": "",
    "Electronegativity": "1.3",
    "FirstIonizationPotential": "6.42",
    "Density": "13.5",
    "MeltingPoint": "1133.15",
    "BoilingPoint": "",
    "Isotopes": "123",
    "SpecificHeatCapacity": "",
    "ElectronConfiguration": "",
    "DisplayRow": "9",
    "DisplayColumn": "13",
    "Id": 99,
    "Guid": "9a6fde62-2410-4ea4-ac13-58ec045dcde7",
    "TimeAdded": "2023-09-21T04:51:35.568782+00:00",
    "UserAddedId": 1,
    "TimeModified": "2023-09-21T04:51:35.568782+00:00",
    "UserModifiedId": 1,
    "IsActive": true
  },
  {
    "AtomicNumber": "100",
    "ElementName": "Fermium",
    "Symbol": "Fm",
    "AtomicWeight": "257",
    "Period": "7",
    "Group": "29",
    "IonicRadius": "",
    "AtomicRadius": "",
    "Electronegativity": "1.3",
    "FirstIonizationPotential": "6.5",
    "Density": "",
    "MeltingPoint": "",
    "BoilingPoint": "",
    "Isotopes": "103",
    "SpecificHeatCapacity": "",
    "ElectronConfiguration": "",
    "DisplayRow": "9",
    "DisplayColumn": "14",
    "Id": 100,
    "Guid": "16da9cfe-afa1-4c7f-ad76-b06106d7d583",
    "TimeAdded": "2023-09-21T04:51:35.568782+00:00",
    "UserAddedId": 1,
    "TimeModified": "2023-09-21T04:51:35.568782+00:00",
    "UserModifiedId": 1,
    "IsActive": true
  },
  {
    "AtomicNumber": "101",
    "ElementName": "Mendelevium",
    "Symbol": "Md",
    "AtomicWeight": "258",
    "Period": "7",
    "Group": "30",
    "IonicRadius": "",
    "AtomicRadius": "",
    "Electronegativity": "1.3",
    "FirstIonizationPotential": "6.58",
    "Density": "",
    "MeltingPoint": "",
    "BoilingPoint": "",
    "Isotopes": "33",
    "SpecificHeatCapacity": "",
    "ElectronConfiguration": "",
    "DisplayRow": "9",
    "DisplayColumn": "15",
    "Id": 101,
    "Guid": "13250812-5d25-41bc-8378-1aa5963bc3aa",
    "TimeAdded": "2023-09-21T04:51:35.568782+00:00",
    "UserAddedId": 1,
    "TimeModified": "2023-09-21T04:51:35.568782+00:00",
    "UserModifiedId": 1,
    "IsActive": true
  },
  {
    "AtomicNumber": "102",
    "ElementName": "Nobelium",
    "Symbol": "No",
    "AtomicWeight": "259",
    "Period": "7",
    "Group": "31",
    "IonicRadius": "",
    "AtomicRadius": "",
    "Electronegativity": "1.3",
    "FirstIonizationPotential": "6.65",
    "Density": "",
    "MeltingPoint": "",
    "BoilingPoint": "",
    "Isotopes": "73",
    "SpecificHeatCapacity": "",
    "ElectronConfiguration": "",
    "DisplayRow": "9",
    "DisplayColumn": "16",
    "Id": 102,
    "Guid": "b327d96d-b8bb-4427-be9e-630fdf7b9483",
    "TimeAdded": "2023-09-21T04:51:35.568782+00:00",
    "UserAddedId": 1,
    "TimeModified": "2023-09-21T04:51:35.568782+00:00",
    "UserModifiedId": 1,
    "IsActive": true
  },
  {
    "AtomicNumber": "103",
    "ElementName": "Lawrencium",
    "Symbol": "Lr",
    "AtomicWeight": "262",
    "Period": "7",
    "Group": "32",
    "IonicRadius": "",
    "AtomicRadius": "",
    "Electronegativity": "",
    "FirstIonizationPotential": "",
    "Density": "",
    "MeltingPoint": "",
    "BoilingPoint": "",
    "Isotopes": "203",
    "SpecificHeatCapacity": "",
    "ElectronConfiguration": "",
    "DisplayRow": "9",
    "DisplayColumn": "17",
    "Id": 103,
    "Guid": "726e5be3-baf2-4209-a1c7-0e02a11a4a37",
    "TimeAdded": "2023-09-21T04:51:35.568782+00:00",
    "UserAddedId": 1,
    "TimeModified": "2023-09-21T04:51:35.568782+00:00",
    "UserModifiedId": 1,
    "IsActive": true
  },
  {
    "AtomicNumber": "104",
    "ElementName": "Rutherfordium",
    "Symbol": "Rf",
    "AtomicWeight": "261",
    "Period": "7",
    "Group": "4",
    "IonicRadius": "",
    "AtomicRadius": "",
    "Electronegativity": "",
    "FirstIonizationPotential": "",
    "Density": "18.1",
    "MeltingPoint": "",
    "BoilingPoint": "",
    "Isotopes": "",
    "SpecificHeatCapacity": "",
    "ElectronConfiguration": "",
    "DisplayRow": "7",
    "DisplayColumn": "4",
    "Id": 104,
    "Guid": "0df6b946-aa14-487c-b2c2-8eb54accc380",
    "TimeAdded": "2023-09-21T04:51:35.568782+00:00",
    "UserAddedId": 1,
    "TimeModified": "2023-09-21T04:51:35.568782+00:00",
    "UserModifiedId": 1,
    "IsActive": true
  },
  {
    "AtomicNumber": "105",
    "ElementName": "Dubnium",
    "Symbol": "Db",
    "AtomicWeight": "262",
    "Period": "7",
    "Group": "5",
    "IonicRadius": "",
    "AtomicRadius": "",
    "Electronegativity": "",
    "FirstIonizationPotential": "",
    "Density": "39",
    "MeltingPoint": "",
    "BoilingPoint": "",
    "Isotopes": "",
    "SpecificHeatCapacity": "",
    "ElectronConfiguration": "",
    "DisplayRow": "7",
    "DisplayColumn": "5",
    "Id": 105,
    "Guid": "57a6b44e-1ddb-4d14-9788-77dccf9b28b9",
    "TimeAdded": "2023-09-21T04:51:35.568782+00:00",
    "UserAddedId": 1,
    "TimeModified": "2023-09-21T04:51:35.568782+00:00",
    "UserModifiedId": 1,
    "IsActive": true
  },
  {
    "AtomicNumber": "106",
    "ElementName": "Seaborgium",
    "Symbol": "Sg",
    "AtomicWeight": "266",
    "Period": "7",
    "Group": "6",
    "IonicRadius": "",
    "AtomicRadius": "",
    "Electronegativity": "",
    "FirstIonizationPotential": "",
    "Density": "35",
    "MeltingPoint": "",
    "BoilingPoint": "",
    "Isotopes": "",
    "SpecificHeatCapacity": "",
    "ElectronConfiguration": "",
    "DisplayRow": "7",
    "DisplayColumn": "6",
    "Id": 106,
    "Guid": "a3d7e3fa-249d-408f-9ba2-804295fa10bf",
    "TimeAdded": "2023-09-21T04:51:35.568782+00:00",
    "UserAddedId": 1,
    "TimeModified": "2023-09-21T04:51:35.568782+00:00",
    "UserModifiedId": 1,
    "IsActive": true
  },
  {
    "AtomicNumber": "107",
    "ElementName": "Bohrium",
    "Symbol": "Bh",
    "AtomicWeight": "264",
    "Period": "7",
    "Group": "7",
    "IonicRadius": "",
    "AtomicRadius": "",
    "Electronegativity": "",
    "FirstIonizationPotential": "",
    "Density": "37",
    "MeltingPoint": "",
    "BoilingPoint": "",
    "Isotopes": "",
    "SpecificHeatCapacity": "",
    "ElectronConfiguration": "",
    "DisplayRow": "7",
    "DisplayColumn": "7",
    "Id": 107,
    "Guid": "d792cbdd-fdc3-47bd-8104-4901e36cc0ce",
    "TimeAdded": "2023-09-21T04:51:35.568782+00:00",
    "UserAddedId": 1,
    "TimeModified": "2023-09-21T04:51:35.568782+00:00",
    "UserModifiedId": 1,
    "IsActive": true
  },
  {
    "AtomicNumber": "108",
    "ElementName": "Hassium",
    "Symbol": "Hs",
    "AtomicWeight": "267",
    "Period": "7",
    "Group": "8",
    "IonicRadius": "",
    "AtomicRadius": "",
    "Electronegativity": "",
    "FirstIonizationPotential": "",
    "Density": "41",
    "MeltingPoint": "",
    "BoilingPoint": "",
    "Isotopes": "",
    "SpecificHeatCapacity": "",
    "ElectronConfiguration": "",
    "DisplayRow": "7",
    "DisplayColumn": "8",
    "Id": 108,
    "Guid": "d1667855-b3c7-48bd-96fb-0b5df6aef46e",
    "TimeAdded": "2023-09-21T04:51:35.568782+00:00",
    "UserAddedId": 1,
    "TimeModified": "2023-09-21T04:51:35.568782+00:00",
    "UserModifiedId": 1,
    "IsActive": true
  },
  {
    "AtomicNumber": "109",
    "ElementName": "Meitnerium",
    "Symbol": "Mt",
    "AtomicWeight": "268",
    "Period": "7",
    "Group": "9",
    "IonicRadius": "",
    "AtomicRadius": "",
    "Electronegativity": "",
    "FirstIonizationPotential": "",
    "Density": "35",
    "MeltingPoint": "",
    "BoilingPoint": "",
    "Isotopes": "",
    "SpecificHeatCapacity": "",
    "ElectronConfiguration": "",
    "DisplayRow": "7",
    "DisplayColumn": "9",
    "Id": 109,
    "Guid": "6c57e866-04bf-420d-b0e0-c177f668c1d3",
    "TimeAdded": "2023-09-21T04:51:35.568782+00:00",
    "UserAddedId": 1,
    "TimeModified": "2023-09-21T04:51:35.568782+00:00",
    "UserModifiedId": 1,
    "IsActive": true
  },
  {
    "AtomicNumber": "110",
    "ElementName": "Darmstadtium ",
    "Symbol": "Ds ",
    "AtomicWeight": "271",
    "Period": "7",
    "Group": "10",
    "IonicRadius": "",
    "AtomicRadius": "",
    "Electronegativity": "",
    "FirstIonizationPotential": "",
    "Density": "",
    "MeltingPoint": "",
    "BoilingPoint": "",
    "Isotopes": "",
    "SpecificHeatCapacity": "",
    "ElectronConfiguration": "",
    "DisplayRow": "7",
    "DisplayColumn": "10",
    "Id": 110,
    "Guid": "1c380d26-c44b-45f8-8de3-4d9acf0f1a4b",
    "TimeAdded": "2023-09-21T04:51:35.568782+00:00",
    "UserAddedId": 1,
    "TimeModified": "2023-09-21T04:51:35.568782+00:00",
    "UserModifiedId": 1,
    "IsActive": true
  },
  {
    "AtomicNumber": "111",
    "ElementName": "Roentgenium ",
    "Symbol": "Rg ",
    "AtomicWeight": "272",
    "Period": "7",
    "Group": "11",
    "IonicRadius": "",
    "AtomicRadius": "",
    "Electronegativity": "",
    "FirstIonizationPotential": "",
    "Density": "",
    "MeltingPoint": "",
    "BoilingPoint": "",
    "Isotopes": "",
    "SpecificHeatCapacity": "",
    "ElectronConfiguration": "",
    "DisplayRow": "7",
    "DisplayColumn": "11",
    "Id": 111,
    "Guid": "9b859158-1823-4a19-a13a-448ba026749c",
    "TimeAdded": "2023-09-21T04:51:35.568782+00:00",
    "UserAddedId": 1,
    "TimeModified": "2023-09-21T04:51:35.568782+00:00",
    "UserModifiedId": 1,
    "IsActive": true
  },
  {
    "AtomicNumber": "112",
    "ElementName": "Copernicium ",
    "Symbol": "Cn ",
    "AtomicWeight": "285",
    "Period": "7",
    "Group": "12",
    "IonicRadius": "",
    "AtomicRadius": "",
    "Electronegativity": "",
    "FirstIonizationPotential": "",
    "Density": "",
    "MeltingPoint": "",
    "BoilingPoint": "",
    "Isotopes": "",
    "SpecificHeatCapacity": "",
    "ElectronConfiguration": "",
    "DisplayRow": "7",
    "DisplayColumn": "12",
    "Id": 112,
    "Guid": "94c7e92f-331f-4b6c-b4e7-56a6009cfa32",
    "TimeAdded": "2023-09-21T04:51:35.568782+00:00",
    "UserAddedId": 1,
    "TimeModified": "2023-09-21T04:51:35.568782+00:00",
    "UserModifiedId": 1,
    "IsActive": true
  },
  {
    "AtomicNumber": "113",
    "ElementName": "Ununtrium ",
    "Symbol": "Uut ",
    "AtomicWeight": "284",
    "Period": "7",
    "Group": "13",
    "IonicRadius": "",
    "AtomicRadius": "",
    "Electronegativity": "",
    "FirstIonizationPotential": "",
    "Density": "",
    "MeltingPoint": "",
    "BoilingPoint": "",
    "Isotopes": "",
    "SpecificHeatCapacity": "",
    "ElectronConfiguration": "",
    "DisplayRow": "7",
    "DisplayColumn": "13",
    "Id": 113,
    "Guid": "670715e8-3304-4b0a-8d53-8d81e9379e4c",
    "TimeAdded": "2023-09-21T04:51:35.568782+00:00",
    "UserAddedId": 1,
    "TimeModified": "2023-09-21T04:51:35.568782+00:00",
    "UserModifiedId": 1,
    "IsActive": true
  },
  {
    "AtomicNumber": "114",
    "ElementName": "Ununquadium ",
    "Symbol": "Uuq ",
    "AtomicWeight": "289",
    "Period": "7",
    "Group": "14",
    "IonicRadius": "",
    "AtomicRadius": "",
    "Electronegativity": "",
    "FirstIonizationPotential": "",
    "Density": "",
    "MeltingPoint": "",
    "BoilingPoint": "",
    "Isotopes": "",
    "SpecificHeatCapacity": "",
    "ElectronConfiguration": "",
    "DisplayRow": "7",
    "DisplayColumn": "14",
    "Id": 114,
    "Guid": "10a32c2c-5249-4b2e-8215-ab7dd67806c9",
    "TimeAdded": "2023-09-21T04:51:35.568782+00:00",
    "UserAddedId": 1,
    "TimeModified": "2023-09-21T04:51:35.568782+00:00",
    "UserModifiedId": 1,
    "IsActive": true
  },
  {
    "AtomicNumber": "115",
    "ElementName": "Ununpentium ",
    "Symbol": "Uup ",
    "AtomicWeight": "288",
    "Period": "7",
    "Group": "15",
    "IonicRadius": "",
    "AtomicRadius": "",
    "Electronegativity": "",
    "FirstIonizationPotential": "",
    "Density": "",
    "MeltingPoint": "",
    "BoilingPoint": "",
    "Isotopes": "",
    "SpecificHeatCapacity": "",
    "ElectronConfiguration": "",
    "DisplayRow": "7",
    "DisplayColumn": "15",
    "Id": 115,
    "Guid": "a2c9f235-535d-4e0e-b541-90495830f6c3",
    "TimeAdded": "2023-09-21T04:51:35.568782+00:00",
    "UserAddedId": 1,
    "TimeModified": "2023-09-21T04:51:35.568782+00:00",
    "UserModifiedId": 1,
    "IsActive": true
  },
  {
    "AtomicNumber": "116",
    "ElementName": "Ununhexium ",
    "Symbol": "Uuh ",
    "AtomicWeight": "292",
    "Period": "7",
    "Group": "16",
    "IonicRadius": "",
    "AtomicRadius": "",
    "Electronegativity": "",
    "FirstIonizationPotential": "",
    "Density": "",
    "MeltingPoint": "",
    "BoilingPoint": "",
    "Isotopes": "",
    "SpecificHeatCapacity": "",
    "ElectronConfiguration": "",
    "DisplayRow": "7",
    "DisplayColumn": "16",
    "Id": 116,
    "Guid": "22864dfc-de1c-47a1-9748-363f0a258c63",
    "TimeAdded": "2023-09-21T04:51:35.568782+00:00",
    "UserAddedId": 1,
    "TimeModified": "2023-09-21T04:51:35.568782+00:00",
    "UserModifiedId": 1,
    "IsActive": true
  },
  {
    "AtomicNumber": "117",
    "ElementName": "Ununseptium ",
    "Symbol": "Uus ",
    "AtomicWeight": "295",
    "Period": "7",
    "Group": "17",
    "IonicRadius": "",
    "AtomicRadius": "",
    "Electronegativity": "",
    "FirstIonizationPotential": "",
    "Density": "",
    "MeltingPoint": "",
    "BoilingPoint": "",
    "Isotopes": "",
    "SpecificHeatCapacity": "",
    "ElectronConfiguration": "",
    "DisplayRow": "7",
    "DisplayColumn": "17",
    "Id": 117,
    "Guid": "35d733a2-fe07-485a-8e2a-467d29d1a4f0",
    "TimeAdded": "2023-09-21T04:51:35.568782+00:00",
    "UserAddedId": 1,
    "TimeModified": "2023-09-21T04:51:35.568782+00:00",
    "UserModifiedId": 1,
    "IsActive": true
  },
  {
    "AtomicNumber": "118",
    "ElementName": "Ununoctium ",
    "Symbol": "Uuo ",
    "AtomicWeight": "294",
    "Period": "7",
    "Group": "18",
    "IonicRadius": "",
    "AtomicRadius": "",
    "Electronegativity": "",
    "FirstIonizationPotential": "",
    "Density": "",
    "MeltingPoint": "",
    "BoilingPoint": "",
    "Isotopes": "",
    "SpecificHeatCapacity": "",
    "ElectronConfiguration": "",
    "DisplayRow": "7",
    "DisplayColumn": "18",
    "Id": 118,
    "Guid": "07c47364-4cc4-4d38-9c9d-b78bd259100c",
    "TimeAdded": "2023-09-21T04:51:35.568782+00:00",
    "UserAddedId": 1,
    "TimeModified": "2023-09-21T04:51:35.568782+00:00",
    "UserModifiedId": 1,
    "IsActive": true
  }
]